Workbook

Sheet Dashboard
A1: DASHBOARD EJECUTIVO
A2: ="Mes en curso: "&TEXT(TODAY(),"mmmm yyyy")&" · Actualizado: "&TEXT(NOW(),"dd/mm/yyyy hh:mm") | P2: =IF('Catálogo'!$A2="","",'Catálogo'!$B2) | Q2: =IF('Catálogo'!$A2="","",SUMIF('Ventas'!$D:$D,'Catálogo'!$A2,'Ventas'!$F:$F)) | R2: =IF('Catálogo'!$A2="","",$Q2+ROW()/100000)
P3: =IF('Catálogo'!$A3="","",'Catálogo'!$B3) | Q3: =IF('Catálogo'!$A3="","",SUMIF('Ventas'!$D:$D,'Catálogo'!$A3,'Ventas'!$F:$F)) | R3: =IF('Catálogo'!$A3="","",$Q3+ROW()/100000)
A4: VENTAS DEL MES | D4: GANANCIA DEL MES | G4: COMPRAS DEL MES | J4: VALOR DEL INVENTARIO | P4: =IF('Catálogo'!$A4="","",'Catálogo'!$B4) | Q4: =IF('Catálogo'!$A4="","",SUMIF('Ventas'!$D:$D,'Catálogo'!$A4,'Ventas'!$F:$F)) | R4: =IF('Catálogo'!$A4="","",$Q4+ROW()/100000)
A5: =SUMIFS('Ventas'!$H:$H,'Ventas'!$A:$A,">="&EOMONTH(TODAY(),-1)+1,'Ventas'!$A:$A,"<="&EOMONTH(TODAY(),0)) | D5: =SUMIFS('Ventas'!$L:$L,'Ventas'!$A:$A,">="&EOMONTH(TODAY(),-1)+1,'Ventas'!$A:$A,"<="&EOMONTH(TODAY(),0)) | G5: =SUMIFS('Compras'!$F:$F,'Compras'!$A:$A,">="&EOMONTH(TODAY(),-1)+1,'Compras'!$A:$A,"<="&EOMONTH(TODAY(),0)) | J5: =SUM('Catálogo'!$J$2:$J$201) | P5: =IF('Catálogo'!$A5="","",'Catálogo'!$B5) | Q5: =IF('Catálogo'!$A5="","",SUMIF('Ventas'!$D:$D,'Catálogo'!$A5,'Ventas'!$F:$F)) | R5: =IF('Catálogo'!$A5="","",$Q5+ROW()/100000)
P6: =IF('Catálogo'!$A6="","",'Catálogo'!$B6) | Q6: =IF('Catálogo'!$A6="","",SUMIF('Ventas'!$D:$D,'Catálogo'!$A6,'Ventas'!$F:$F)) | R6: =IF('Catálogo'!$A6="","",$Q6+ROW()/100000)
A7: INVENTARIO EN CASA (UNID) | D7: INVENTARIO EN ML (UNID) | G7: PRODUCTOS CON STOCK BAJO | J7: PRODUCTOS AGOTADOS | P7: =IF('Catálogo'!$A7="","",'Catálogo'!$B7) | Q7: =IF('Catálogo'!$A7="","",SUMIF('Ventas'!$D:$D,'Catálogo'!$A7,'Ventas'!$F:$F)) | R7: =IF('Catálogo'!$A7="","",$Q7+ROW()/100000)
A8: =SUM('Catálogo'!$G$2:$G$201) | D8: =SUM('Catálogo'!$H$2:$H$201) | G8: =COUNTIF('Catálogo'!$K$2:$K$201,"Stock bajo") | J8: =COUNTIF('Catálogo'!$K$2:$K$201,"Agotado") | P8: =IF('Catálogo'!$A8="","",'Catálogo'!$B8) | Q8: =IF('Catálogo'!$A8="","",SUMIF('Ventas'!$D:$D,'Catálogo'!$A8,'Ventas'!$F:$F)) | R8: =IF('Catálogo'!$A8="","",$Q8+ROW()/100000)
P9: =IF('Catálogo'!$A9="","",'Catálogo'!$B9) | Q9: =IF('Catálogo'!$A9="","",SUMIF('Ventas'!$D:$D,'Catálogo'!$A9,'Ventas'!$F:$F)) | R9: =IF('Catálogo'!$A9="","",$Q9+ROW()/100000)
P10: =IF('Catálogo'!$A10="","",'Catálogo'!$B10) | Q10: =IF('Catálogo'!$A10="","",SUMIF('Ventas'!$D:$D,'Catálogo'!$A10,'Ventas'!$F:$F)) | R10: =IF('Catálogo'!$A10="","",$Q10+ROW()/100000)
A11: 🏆 PRODUCTOS MÁS VENDIDOS | G11: ⚠️ ALERTAS DE INVENTARIO (bajo / agotado) | P11: =IF('Catálogo'!$A11="","",'Catálogo'!$B11) | Q11: =IF('Catálogo'!$A11="","",SUMIF('Ventas'!$D:$D,'Catálogo'!$A11,'Ventas'!$F:$F)) | R11: =IF('Catálogo'!$A11="","",$Q11+ROW()/100000)
A12: Producto | E12: Unid. | G12: Producto | J12: Casa | K12: ML | L12: Total | P12: =IF('Catálogo'!$A12="","",'Catálogo'!$B12) | Q12: =IF('Catálogo'!$A12="","",SUMIF('Ventas'!$D:$D,'Catálogo'!$A12,'Ventas'!$F:$F)) | R12: =IF('Catálogo'!$A12="","",$Q12+ROW()/100000)
A13: =IFERROR(IF(INT(LARGE($R$2:$R$201,1))=0,"",INDEX($P$2:$P$201,MATCH(LARGE($R$2:$R$201,1),$R$2:$R$201,0))),"") | E13: =IFERROR(IF(INT(LARGE($R$2:$R$201,1))=0,"",INT(LARGE($R$2:$R$201,1))),"") | G13: =IF(OR('Catálogo'!$K2="Agotado",'Catálogo'!$K2="Stock bajo"),'Catálogo'!$B2,"") | J13: =IF(OR('Catálogo'!$K2="Agotado",'Catálogo'!$K2="Stock bajo"),'Catálogo'!$G2,"") | K13: =IF(OR('Catálogo'!$K2="Agotado",'Catálogo'!$K2="Stock bajo"),'Catálogo'!$H2,"") | L13: =IF(OR('Catálogo'!$K2="Agotado",'Catálogo'!$K2="Stock bajo"),'Catálogo'!$I2,"") | P13: =IF('Catálogo'!$A13="","",'Catálogo'!$B13) | Q13: =IF('Catálogo'!$A13="","",SUMIF('Ventas'!$D:$D,'Catálogo'!$A13,'Ventas'!$F:$F)) | R13: =IF('Catálogo'!$A13="","",$Q13+ROW()/100000)
A14: =IFERROR(IF(INT(LARGE($R$2:$R$201,2))=0,"",INDEX($P$2:$P$201,MATCH(LARGE($R$2:$R$201,2),$R$2:$R$201,0))),"") | E14: =IFERROR(IF(INT(LARGE($R$2:$R$201,2))=0,"",INT(LARGE($R$2:$R$201,2))),"") | G14: =IF(OR('Catálogo'!$K3="Agotado",'Catálogo'!$K3="Stock bajo"),'Catálogo'!$B3,"") | J14: =IF(OR('Catálogo'!$K3="Agotado",'Catálogo'!$K3="Stock bajo"),'Catálogo'!$G3,"") | K14: =IF(OR('Catálogo'!$K3="Agotado",'Catálogo'!$K3="Stock bajo"),'Catálogo'!$H3,"") | L14: =IF(OR('Catálogo'!$K3="Agotado",'Catálogo'!$K3="Stock bajo"),'Catálogo'!$I3,"") | P14: =IF('Catálogo'!$A14="","",'Catálogo'!$B14) | Q14: =IF('Catálogo'!$A14="","",SUMIF('Ventas'!$D:$D,'Catálogo'!$A14,'Ventas'!$F:$F)) | R14: =IF('Catálogo'!$A14="","",$Q14+ROW()/100000)
A15: =IFERROR(IF(INT(LARGE($R$2:$R$201,3))=0,"",INDEX($P$2:$P$201,MATCH(LARGE($R$2:$R$201,3),$R$2:$R$201,0))),"") | E15: =IFERROR(IF(INT(LARGE($R$2:$R$201,3))=0,"",INT(LARGE($R$2:$R$201,3))),"") | G15: =IF(OR('Catálogo'!$K4="Agotado",'Catálogo'!$K4="Stock bajo"),'Catálogo'!$B4,"") | J15: =IF(OR('Catálogo'!$K4="Agotado",'Catálogo'!$K4="Stock bajo"),'Catálogo'!$G4,"") | K15: =IF(OR('Catálogo'!$K4="Agotado",'Catálogo'!$K4="Stock bajo"),'Catálogo'!$H4,"") | L15: =IF(OR('Catálogo'!$K4="Agotado",'Catálogo'!$K4="Stock bajo"),'Catálogo'!$I4,"") | P15: =IF('Catálogo'!$A15="","",'Catálogo'!$B15) | Q15: =IF('Catálogo'!$A15="","",SUMIF('Ventas'!$D:$D,'Catálogo'!$A15,'Ventas'!$F:$F)) | R15: =IF('Catálogo'!$A15="","",$Q15+ROW()/100000)
A16: =IFERROR(IF(INT(LARGE($R$2:$R$201,4))=0,"",INDEX($P$2:$P$201,MATCH(LARGE($R$2:$R$201,4),$R$2:$R$201,0))),"") | E16: =IFERROR(IF(INT(LARGE($R$2:$R$201,4))=0,"",INT(LARGE($R$2:$R$201,4))),"") | G16: =IF(OR('Catálogo'!$K5="Agotado",'Catálogo'!$K5="Stock bajo"),'Catálogo'!$B5,"") | J16: =IF(OR('Catálogo'!$K5="Agotado",'Catálogo'!$K5="Stock bajo"),'Catálogo'!$G5,"") | K16: =IF(OR('Catálogo'!$K5="Agotado",'Catálogo'!$K5="Stock bajo"),'Catálogo'!$H5,"") | L16: =IF(OR('Catálogo'!$K5="Agotado",'Catálogo'!$K5="Stock bajo"),'Catálogo'!$I5,"") | P16: =IF('Catálogo'!$A16="","",'Catálogo'!$B16) | Q16: =IF('Catálogo'!$A16="","",SUMIF('Ventas'!$D:$D,'Catálogo'!$A16,'Ventas'!$F:$F)) | R16: =IF('Catálogo'!$A16="","",$Q16+ROW()/100000)
A17: =IFERROR(IF(INT(LARGE($R$2:$R$201,5))=0,"",INDEX($P$2:$P$201,MATCH(LARGE($R$2:$R$201,5),$R$2:$R$201,0))),"") | E17: =IFERROR(IF(INT(LARGE($R$2:$R$201,5))=0,"",INT(LARGE($R$2:$R$201,5))),"") | G17: =IF(OR('Catálogo'!$K6="Agotado",'Catálogo'!$K6="Stock bajo"),'Catálogo'!$B6,"") | J17: =IF(OR('Catálogo'!$K6="Agotado",'Catálogo'!$K6="Stock bajo"),'Catálogo'!$G6,"") | K17: =IF(OR('Catálogo'!$K6="Agotado",'Catálogo'!$K6="Stock bajo"),'Catálogo'!$H6,"") | L17: =IF(OR('Catálogo'!$K6="Agotado",'Catálogo'!$K6="Stock bajo"),'Catálogo'!$I6,"") | P17: =IF('Catálogo'!$A17="","",'Catálogo'!$B17) | Q17: =IF('Catálogo'!$A17="","",SUMIF('Ventas'!$D:$D,'Catálogo'!$A17,'Ventas'!$F:$F)) | R17: =IF('Catálogo'!$A17="","",$Q17+ROW()/100000)
A18: =IFERROR(IF(INT(LARGE($R$2:$R$201,6))=0,"",INDEX($P$2:$P$201,MATCH(LARGE($R$2:$R$201,6),$R$2:$R$201,0))),"") | E18: =IFERROR(IF(INT(LARGE($R$2:$R$201,6))=0,"",INT(LARGE($R$2:$R$201,6))),"") | G18: =IF(OR('Catálogo'!$K7="Agotado",'Catálogo'!$K7="Stock bajo"),'Catálogo'!$B7,"") | J18: =IF(OR('Catálogo'!$K7="Agotado",'Catálogo'!$K7="Stock bajo"),'Catálogo'!$G7,"") | K18: =IF(OR('Catálogo'!$K7="Agotado",'Catálogo'!$K7="Stock bajo"),'Catálogo'!$H7,"") | L18: =IF(OR('Catálogo'!$K7="Agotado",'Catálogo'!$K7="Stock bajo"),'Catálogo'!$I7,"") | P18: =IF('Catálogo'!$A18="","",'Catálogo'!$B18) | Q18: =IF('Catálogo'!$A18="","",SUMIF('Ventas'!$D:$D,'Catálogo'!$A18,'Ventas'!$F:$F)) | R18: =IF('Catálogo'!$A18="","",$Q18+ROW()/100000)
A19: =IFERROR(IF(INT(LARGE($R$2:$R$201,7))=0,"",INDEX($P$2:$P$201,MATCH(LARGE($R$2:$R$201,7),$R$2:$R$201,0))),"") | E19: =IFERROR(IF(INT(LARGE($R$2:$R$201,7))=0,"",INT(LARGE($R$2:$R$201,7))),"") | G19: =IF(OR('Catálogo'!$K8="Agotado",'Catálogo'!$K8="Stock bajo"),'Catálogo'!$B8,"") | J19: =IF(OR('Catálogo'!$K8="Agotado",'Catálogo'!$K8="Stock bajo"),'Catálogo'!$G8,"") | K19: =IF(OR('Catálogo'!$K8="Agotado",'Catálogo'!$K8="Stock bajo"),'Catálogo'!$H8,"") | L19: =IF(OR('Catálogo'!$K8="Agotado",'Catálogo'!$K8="Stock bajo"),'Catálogo'!$I8,"") | P19: =IF('Catálogo'!$A19="","",'Catálogo'!$B19) | Q19: =IF('Catálogo'!$A19="","",SUMIF('Ventas'!$D:$D,'Catálogo'!$A19,'Ventas'!$F:$F)) | R19: =IF('Catálogo'!$A19="","",$Q19+ROW()/100000)
A20: =IFERROR(IF(INT(LARGE($R$2:$R$201,8))=0,"",INDEX($P$2:$P$201,MATCH(LARGE($R$2:$R$201,8),$R$2:$R$201,0))),"") | E20: =IFERROR(IF(INT(LARGE($R$2:$R$201,8))=0,"",INT(LARGE($R$2:$R$201,8))),"") | G20: =IF(OR('Catálogo'!$K9="Agotado",'Catálogo'!$K9="Stock bajo"),'Catálogo'!$B9,"") | J20: =IF(OR('Catálogo'!$K9="Agotado",'Catálogo'!$K9="Stock bajo"),'Catálogo'!$G9,"") | K20: =IF(OR('Catálogo'!$K9="Agotado",'Catálogo'!$K9="Stock bajo"),'Catálogo'!$H9,"") | L20: =IF(OR('Catálogo'!$K9="Agotado",'Catálogo'!$K9="Stock bajo"),'Catálogo'!$I9,"") | P20: =IF('Catálogo'!$A20="","",'Catálogo'!$B20) | Q20: =IF('Catálogo'!$A20="","",SUMIF('Ventas'!$D:$D,'Catálogo'!$A20,'Ventas'!$F:$F)) | R20: =IF('Catálogo'!$A20="","",$Q20+ROW()/100000)
G21: =IF(OR('Catálogo'!$K10="Agotado",'Catálogo'!$K10="Stock bajo"),'Catálogo'!$B10,"") | J21: =IF(OR('Catálogo'!$K10="Agotado",'Catálogo'!$K10="Stock bajo"),'Catálogo'!$G10,"") | K21: =IF(OR('Catálogo'!$K10="Agotado",'Catálogo'!$K10="Stock bajo"),'Catálogo'!$H10,"") | L21: =IF(OR('Catálogo'!$K10="Agotado",'Catálogo'!$K10="Stock bajo"),'Catálogo'!$I10,"") | P21: =IF('Catálogo'!$A21="","",'Catálogo'!$B21) | Q21: =IF('Catálogo'!$A21="","",SUMIF('Ventas'!$D:$D,'Catálogo'!$A21,'Ventas'!$F:$F)) | R21: =IF('Catálogo'!$A21="","",$Q21+ROW()/100000)
G22: =IF(OR('Catálogo'!$K11="Agotado",'Catálogo'!$K11="Stock bajo"),'Catálogo'!$B11,"") | J22: =IF(OR('Catálogo'!$K11="Agotado",'Catálogo'!$K11="Stock bajo"),'Catálogo'!$G11,"") | K22: =IF(OR('Catálogo'!$K11="Agotado",'Catálogo'!$K11="Stock bajo"),'Catálogo'!$H11,"") | L22: =IF(OR('Catálogo'!$K11="Agotado",'Catálogo'!$K11="Stock bajo"),'Catálogo'!$I11,"") | P22: =IF('Catálogo'!$A22="","",'Catálogo'!$B22) | Q22: =IF('Catálogo'!$A22="","",SUMIF('Ventas'!$D:$D,'Catálogo'!$A22,'Ventas'!$F:$F)) | R22: =IF('Catálogo'!$A22="","",$Q22+ROW()/100000)
G23: =IF(OR('Catálogo'!$K12="Agotado",'Catálogo'!$K12="Stock bajo"),'Catálogo'!$B12,"") | J23: =IF(OR('Catálogo'!$K12="Agotado",'Catálogo'!$K12="Stock bajo"),'Catálogo'!$G12,"") | K23: =IF(OR('Catálogo'!$K12="Agotado",'Catálogo'!$K12="Stock bajo"),'Catálogo'!$H12,"") | L23: =IF(OR('Catálogo'!$K12="Agotado",'Catálogo'!$K12="Stock bajo"),'Catálogo'!$I12,"") | P23: =IF('Catálogo'!$A23="","",'Catálogo'!$B23) | Q23: =IF('Catálogo'!$A23="","",SUMIF('Ventas'!$D:$D,'Catálogo'!$A23,'Ventas'!$F:$F)) | R23: =IF('Catálogo'!$A23="","",$Q23+ROW()/100000)
G24: =IF(OR('Catálogo'!$K13="Agotado",'Catálogo'!$K13="Stock bajo"),'Catálogo'!$B13,"") | J24: =IF(OR('Catálogo'!$K13="Agotado",'Catálogo'!$K13="Stock bajo"),'Catálogo'!$G13,"") | K24: =IF(OR('Catálogo'!$K13="Agotado",'Catálogo'!$K13="Stock bajo"),'Catálogo'!$H13,"") | L24: =IF(OR('Catálogo'!$K13="Agotado",'Catálogo'!$K13="Stock bajo"),'Catálogo'!$I13,"") | P24: =IF('Catálogo'!$A24="","",'Catálogo'!$B24) | Q24: =IF('Catálogo'!$A24="","",SUMIF('Ventas'!$D:$D,'Catálogo'!$A24,'Ventas'!$F:$F)) | R24: =IF('Catálogo'!$A24="","",$Q24+ROW()/100000)
P25: =IF('Catálogo'!$A25="","",'Catálogo'!$B25) | Q25: =IF('Catálogo'!$A25="","",SUMIF('Ventas'!$D:$D,'Catálogo'!$A25,'Ventas'!$F:$F)) | R25: =IF('Catálogo'!$A25="","",$Q25+ROW()/100000)
A26: 📈 TENDENCIAS (últimos 6 meses) — selecciona A27:D33 e inserta un gráfico | P26: =IF('Catálogo'!$A26="","",'Catálogo'!$B26) | Q26: =IF('Catálogo'!$A26="","",SUMIF('Ventas'!$D:$D,'Catálogo'!$A26,'Ventas'!$F:$F)) | R26: =IF('Catálogo'!$A26="","",$Q26+ROW()/100000)
A27: Mes | B27: Ventas | C27: Utilidad | D27: Compras | P27: =IF('Catálogo'!$A27="","",'Catálogo'!$B27) | Q27: =IF('Catálogo'!$A27="","",SUMIF('Ventas'!$D:$D,'Catálogo'!$A27,'Ventas'!$F:$F)) | R27: =IF('Catálogo'!$A27="","",$Q27+ROW()/100000)
A28: =TEXT(DATE(YEAR(EOMONTH(TODAY(),-5)),MONTH(EOMONTH(TODAY(),-5)),1),"mmm yy") | B28: =SUMIFS('Ventas'!$H:$H,'Ventas'!$A:$A,">="&DATE(YEAR(EOMONTH(TODAY(),-5)),MONTH(EOMONTH(TODAY(),-5)),1),'Ventas'!$A:$A,"<="&EOMONTH(TODAY(),-5)) | C28: =SUMIFS('Ventas'!$L:$L,'Ventas'!$A:$A,">="&DATE(YEAR(EOMONTH(TODAY(),-5)),MONTH(EOMONTH(TODAY(),-5)),1),'Ventas'!$A:$A,"<="&EOMONTH(TODAY(),-5)) | D28: =SUMIFS('Compras'!$F:$F,'Compras'!$A:$A,">="&DATE(YEAR(EOMONTH(TODAY(),-5)),MONTH(EOMONTH(TODAY(),-5)),1),'Compras'!$A:$A,"<="&EOMONTH(TODAY(),-5)) | P28: =IF('Catálogo'!$A28="","",'Catálogo'!$B28) | Q28: =IF('Catálogo'!$A28="","",SUMIF('Ventas'!$D:$D,'Catálogo'!$A28,'Ventas'!$F:$F)) | R28: =IF('Catálogo'!$A28="","",$Q28+ROW()/100000)
A29: =TEXT(DATE(YEAR(EOMONTH(TODAY(),-4)),MONTH(EOMONTH(TODAY(),-4)),1),"mmm yy") | B29: =SUMIFS('Ventas'!$H:$H,'Ventas'!$A:$A,">="&DATE(YEAR(EOMONTH(TODAY(),-4)),MONTH(EOMONTH(TODAY(),-4)),1),'Ventas'!$A:$A,"<="&EOMONTH(TODAY(),-4)) | C29: =SUMIFS('Ventas'!$L:$L,'Ventas'!$A:$A,">="&DATE(YEAR(EOMONTH(TODAY(),-4)),MONTH(EOMONTH(TODAY(),-4)),1),'Ventas'!$A:$A,"<="&EOMONTH(TODAY(),-4)) | D29: =SUMIFS('Compras'!$F:$F,'Compras'!$A:$A,">="&DATE(YEAR(EOMONTH(TODAY(),-4)),MONTH(EOMONTH(TODAY(),-4)),1),'Compras'!$A:$A,"<="&EOMONTH(TODAY(),-4)) | P29: =IF('Catálogo'!$A29="","",'Catálogo'!$B29) | Q29: =IF('Catálogo'!$A29="","",SUMIF('Ventas'!$D:$D,'Catálogo'!$A29,'Ventas'!$F:$F)) | R29: =IF('Catálogo'!$A29="","",$Q29+ROW()/100000)
A30: =TEXT(DATE(YEAR(EOMONTH(TODAY(),-3)),MONTH(EOMONTH(TODAY(),-3)),1),"mmm yy") | B30: =SUMIFS('Ventas'!$H:$H,'Ventas'!$A:$A,">="&DATE(YEAR(EOMONTH(TODAY(),-3)),MONTH(EOMONTH(TODAY(),-3)),1),'Ventas'!$A:$A,"<="&EOMONTH(TODAY(),-3)) | C30: =SUMIFS('Ventas'!$L:$L,'Ventas'!$A:$A,">="&DATE(YEAR(EOMONTH(TODAY(),-3)),MONTH(EOMONTH(TODAY(),-3)),1),'Ventas'!$A:$A,"<="&EOMONTH(TODAY(),-3)) | D30: =SUMIFS('Compras'!$F:$F,'Compras'!$A:$A,">="&DATE(YEAR(EOMONTH(TODAY(),-3)),MONTH(EOMONTH(TODAY(),-3)),1),'Compras'!$A:$A,"<="&EOMONTH(TODAY(),-3)) | P30: =IF('Catálogo'!$A30="","",'Catálogo'!$B30) | Q30: =IF('Catálogo'!$A30="","",SUMIF('Ventas'!$D:$D,'Catálogo'!$A30,'Ventas'!$F:$F)) | R30: =IF('Catálogo'!$A30="","",$Q30+ROW()/100000)
A31: =TEXT(DATE(YEAR(EOMONTH(TODAY(),-2)),MONTH(EOMONTH(TODAY(),-2)),1),"mmm yy") | B31: =SUMIFS('Ventas'!$H:$H,'Ventas'!$A:$A,">="&DATE(YEAR(EOMONTH(TODAY(),-2)),MONTH(EOMONTH(TODAY(),-2)),1),'Ventas'!$A:$A,"<="&EOMONTH(TODAY(),-2)) | C31: =SUMIFS('Ventas'!$L:$L,'Ventas'!$A:$A,">="&DATE(YEAR(EOMONTH(TODAY(),-2)),MONTH(EOMONTH(TODAY(),-2)),1),'Ventas'!$A:$A,"<="&EOMONTH(TODAY(),-2)) | D31: =SUMIFS('Compras'!$F:$F,'Compras'!$A:$A,">="&DATE(YEAR(EOMONTH(TODAY(),-2)),MONTH(EOMONTH(TODAY(),-2)),1),'Compras'!$A:$A,"<="&EOMONTH(TODAY(),-2)) | P31: =IF('Catálogo'!$A31="","",'Catálogo'!$B31) | Q31: =IF('Catálogo'!$A31="","",SUMIF('Ventas'!$D:$D,'Catálogo'!$A31,'Ventas'!$F:$F)) | R31: =IF('Catálogo'!$A31="","",$Q31+ROW()/100000)
A32: =TEXT(DATE(YEAR(EOMONTH(TODAY(),-1)),MONTH(EOMONTH(TODAY(),-1)),1),"mmm yy") | B32: =SUMIFS('Ventas'!$H:$H,'Ventas'!$A:$A,">="&DATE(YEAR(EOMONTH(TODAY(),-1)),MONTH(EOMONTH(TODAY(),-1)),1),'Ventas'!$A:$A,"<="&EOMONTH(TODAY(),-1)) | C32: =SUMIFS('Ventas'!$L:$L,'Ventas'!$A:$A,">="&DATE(YEAR(EOMONTH(TODAY(),-1)),MONTH(EOMONTH(TODAY(),-1)),1),'Ventas'!$A:$A,"<="&EOMONTH(TODAY(),-1)) | D32: =SUMIFS('Compras'!$F:$F,'Compras'!$A:$A,">="&DATE(YEAR(EOMONTH(TODAY(),-1)),MONTH(EOMONTH(TODAY(),-1)),1),'Compras'!$A:$A,"<="&EOMONTH(TODAY(),-1)) | P32: =IF('Catálogo'!$A32="","",'Catálogo'!$B32) | Q32: =IF('Catálogo'!$A32="","",SUMIF('Ventas'!$D:$D,'Catálogo'!$A32,'Ventas'!$F:$F)) | R32: =IF('Catálogo'!$A32="","",$Q32+ROW()/100000)
A33: =TEXT(DATE(YEAR(EOMONTH(TODAY(),0)),MONTH(EOMONTH(TODAY(),0)),1),"mmm yy") | B33: =SUMIFS('Ventas'!$H:$H,'Ventas'!$A:$A,">="&DATE(YEAR(EOMONTH(TODAY(),0)),MONTH(EOMONTH(TODAY(),0)),1),'Ventas'!$A:$A,"<="&EOMONTH(TODAY(),0)) | C33: =SUMIFS('Ventas'!$L:$L,'Ventas'!$A:$A,">="&DATE(YEAR(EOMONTH(TODAY(),0)),MONTH(EOMONTH(TODAY(),0)),1),'Ventas'!$A:$A,"<="&EOMONTH(TODAY(),0)) | D33: =SUMIFS('Compras'!$F:$F,'Compras'!$A:$A,">="&DATE(YEAR(EOMONTH(TODAY(),0)),MONTH(EOMONTH(TODAY(),0)),1),'Compras'!$A:$A,"<="&EOMONTH(TODAY(),0)) | P33: =IF('Catálogo'!$A33="","",'Catálogo'!$B33) | Q33: =IF('Catálogo'!$A33="","",SUMIF('Ventas'!$D:$D,'Catálogo'!$A33,'Ventas'!$F:$F)) | R33: =IF('Catálogo'!$A33="","",$Q33+ROW()/100000)
P34: =IF('Catálogo'!$A34="","",'Catálogo'!$B34) | Q34: =IF('Catálogo'!$A34="","",SUMIF('Ventas'!$D:$D,'Catálogo'!$A34,'Ventas'!$F:$F)) | R34: =IF('Catálogo'!$A34="","",$Q34+ROW()/100000)
A35: DEUDA TOTAL EN TARJETAS | D35: PEDIDOS POR PAGAR | G35: PAGOS VENCIDOS | P35: =IF('Catálogo'!$A35="","",'Catálogo'!$B35) | Q35: =IF('Catálogo'!$A35="","",SUMIF('Ventas'!$D:$D,'Catálogo'!$A35,'Ventas'!$F:$F)) | R35: =IF('Catálogo'!$A35="","",$Q35+ROW()/100000)
A36: =SUM('Tarjetas'!$D$3:$D$10) | D36: =COUNTIF('Compras'!$M:$M,"Pendiente")+COUNTIF('Compras'!$M:$M,"Abono parcial") | G36: =SUMPRODUCT(('Compras'!$N$2:$N$301<>"")*(LEFT('Compras'!$N$2:$N$301,4)="🔴")) | P36: =IF('Catálogo'!$A36="","",'Catálogo'!$B36) | Q36: =IF('Catálogo'!$A36="","",SUMIF('Ventas'!$D:$D,'Catálogo'!$A36,'Ventas'!$F:$F)) | R36: =IF('Catálogo'!$A36="","",$Q36+ROW()/100000)
P37: =IF('Catálogo'!$A37="","",'Catálogo'!$B37) | Q37: =IF('Catálogo'!$A37="","",SUMIF('Ventas'!$D:$D,'Catálogo'!$A37,'Ventas'!$F:$F)) | R37: =IF('Catálogo'!$A37="","",$Q37+ROW()/100000)
A38: 💳 PAGOS DE TARJETA / CRÉDITO PENDIENTES | P38: =IF('Catálogo'!$A38="","",'Catálogo'!$B38) | Q38: =IF('Catálogo'!$A38="","",SUMIF('Ventas'!$D:$D,'Catálogo'!$A38,'Ventas'!$F:$F)) | R38: =IF('Catálogo'!$A38="","",$Q38+ROW()/100000)
A39: Fecha | B39: Producto | E39: Medio de pago | G39: Saldo | H39: Límite pago | I39: Aviso | P39: =IF('Catálogo'!$A39="","",'Catálogo'!$B39) | Q39: =IF('Catálogo'!$A39="","",SUMIF('Ventas'!$D:$D,'Catálogo'!$A39,'Ventas'!$F:$F)) | R39: =IF('Catálogo'!$A39="","",$Q39+ROW()/100000)
A40: =IF(AND('Compras'!$H2="Sí",'Compras'!$L2>0),'Compras'!$A2,"") | B40: =IF(AND('Compras'!$H2="Sí",'Compras'!$L2>0),'Compras'!$C2,"") | E40: =IF(AND('Compras'!$H2="Sí",'Compras'!$L2>0),'Compras'!$G2,"") | G40: =IF(AND('Compras'!$H2="Sí",'Compras'!$L2>0),'Compras'!$L2,"") | H40: =IF(AND('Compras'!$H2="Sí",'Compras'!$L2>0),'Compras'!$J2,"") | I40: =IF(AND('Compras'!$H2="Sí",'Compras'!$L2>0),'Compras'!$N2,"") | P40: =IF('Catálogo'!$A40="","",'Catálogo'!$B40) | Q40: =IF('Catálogo'!$A40="","",SUMIF('Ventas'!$D:$D,'Catálogo'!$A40,'Ventas'!$F:$F)) | R40: =IF('Catálogo'!$A40="","",$Q40+ROW()/100000)
A41: =IF(AND('Compras'!$H3="Sí",'Compras'!$L3>0),'Compras'!$A3,"") | B41: =IF(AND('Compras'!$H3="Sí",'Compras'!$L3>0),'Compras'!$C3,"") | E41: =IF(AND('Compras'!$H3="Sí",'Compras'!$L3>0),'Compras'!$G3,"") | G41: =IF(AND('Compras'!$H3="Sí",'Compras'!$L3>0),'Compras'!$L3,"") | H41: =IF(AND('Compras'!$H3="Sí",'Compras'!$L3>0),'Compras'!$J3,"") | I41: =IF(AND('Compras'!$H3="Sí",'Compras'!$L3>0),'Compras'!$N3,"") | P41: =IF('Catálogo'!$A41="","",'Catálogo'!$B41) | Q41: =IF('Catálogo'!$A41="","",SUMIF('Ventas'!$D:$D,'Catálogo'!$A41,'Ventas'!$F:$F)) | R41: =IF('Catálogo'!$A41="","",$Q41+ROW()/100000)
A42: =IF(AND('Compras'!$H4="Sí",'Compras'!$L4>0),'Compras'!$A4,"") | B42: =IF(AND('Compras'!$H4="Sí",'Compras'!$L4>0),'Compras'!$C4,"") | E42: =IF(AND('Compras'!$H4="Sí",'Compras'!$L4>0),'Compras'!$G4,"") | G42: =IF(AND('Compras'!$H4="Sí",'Compras'!$L4>0),'Compras'!$L4,"") | H42: =IF(AND('Compras'!$H4="Sí",'Compras'!$L4>0),'Compras'!$J4,"") | I42: =IF(AND('Compras'!$H4="Sí",'Compras'!$L4>0),'Compras'!$N4,"") | P42: =IF('Catálogo'!$A42="","",'Catálogo'!$B42) | Q42: =IF('Catálogo'!$A42="","",SUMIF('Ventas'!$D:$D,'Catálogo'!$A42,'Ventas'!$F:$F)) | R42: =IF('Catálogo'!$A42="","",$Q42+ROW()/100000)
A43: =IF(AND('Compras'!$H5="Sí",'Compras'!$L5>0),'Compras'!$A5,"") | B43: =IF(AND('Compras'!$H5="Sí",'Compras'!$L5>0),'Compras'!$C5,"") | E43: =IF(AND('Compras'!$H5="Sí",'Compras'!$L5>0),'Compras'!$G5,"") | G43: =IF(AND('Compras'!$H5="Sí",'Compras'!$L5>0),'Compras'!$L5,"") | H43: =IF(AND('Compras'!$H5="Sí",'Compras'!$L5>0),'Compras'!$J5,"") | I43: =IF(AND('Compras'!$H5="Sí",'Compras'!$L5>0),'Compras'!$N5,"") | P43: =IF('Catálogo'!$A43="","",'Catálogo'!$B43) | Q43: =IF('Catálogo'!$A43="","",SUMIF('Ventas'!$D:$D,'Catálogo'!$A43,'Ventas'!$F:$F)) | R43: =IF('Catálogo'!$A43="","",$Q43+ROW()/100000)
A44: =IF(AND('Compras'!$H6="Sí",'Compras'!$L6>0),'Compras'!$A6,"") | B44: =IF(AND('Compras'!$H6="Sí",'Compras'!$L6>0),'Compras'!$C6,"") | E44: =IF(AND('Compras'!$H6="Sí",'Compras'!$L6>0),'Compras'!$G6,"") | G44: =IF(AND('Compras'!$H6="Sí",'Compras'!$L6>0),'Compras'!$L6,"") | H44: =IF(AND('Compras'!$H6="Sí",'Compras'!$L6>0),'Compras'!$J6,"") | I44: =IF(AND('Compras'!$H6="Sí",'Compras'!$L6>0),'Compras'!$N6,"") | P44: =IF('Catálogo'!$A44="","",'Catálogo'!$B44) | Q44: =IF('Catálogo'!$A44="","",SUMIF('Ventas'!$D:$D,'Catálogo'!$A44,'Ventas'!$F:$F)) | R44: =IF('Catálogo'!$A44="","",$Q44+ROW()/100000)
A45: =IF(AND('Compras'!$H7="Sí",'Compras'!$L7>0),'Compras'!$A7,"") | B45: =IF(AND('Compras'!$H7="Sí",'Compras'!$L7>0),'Compras'!$C7,"") | E45: =IF(AND('Compras'!$H7="Sí",'Compras'!$L7>0),'Compras'!$G7,"") | G45: =IF(AND('Compras'!$H7="Sí",'Compras'!$L7>0),'Compras'!$L7,"") | H45: =IF(AND('Compras'!$H7="Sí",'Compras'!$L7>0),'Compras'!$J7,"") | I45: =IF(AND('Compras'!$H7="Sí",'Compras'!$L7>0),'Compras'!$N7,"") | P45: =IF('Catálogo'!$A45="","",'Catálogo'!$B45) | Q45: =IF('Catálogo'!$A45="","",SUMIF('Ventas'!$D:$D,'Catálogo'!$A45,'Ventas'!$F:$F)) | R45: =IF('Catálogo'!$A45="","",$Q45+ROW()/100000)
A46: =IF(AND('Compras'!$H8="Sí",'Compras'!$L8>0),'Compras'!$A8,"") | B46: =IF(AND('Compras'!$H8="Sí",'Compras'!$L8>0),'Compras'!$C8,"") | E46: =IF(AND('Compras'!$H8="Sí",'Compras'!$L8>0),'Compras'!$G8,"") | G46: =IF(AND('Compras'!$H8="Sí",'Compras'!$L8>0),'Compras'!$L8,"") | H46: =IF(AND('Compras'!$H8="Sí",'Compras'!$L8>0),'Compras'!$J8,"") | I46: =IF(AND('Compras'!$H8="Sí",'Compras'!$L8>0),'Compras'!$N8,"") | P46: =IF('Catálogo'!$A46="","",'Catálogo'!$B46) | Q46: =IF('Catálogo'!$A46="","",SUMIF('Ventas'!$D:$D,'Catálogo'!$A46,'Ventas'!$F:$F)) | R46: =IF('Catálogo'!$A46="","",$Q46+ROW()/100000)
A47: =IF(AND('Compras'!$H9="Sí",'Compras'!$L9>0),'Compras'!$A9,"") | B47: =IF(AND('Compras'!$H9="Sí",'Compras'!$L9>0),'Compras'!$C9,"") | E47: =IF(AND('Compras'!$H9="Sí",'Compras'!$L9>0),'Compras'!$G9,"") | G47: =IF(AND('Compras'!$H9="Sí",'Compras'!$L9>0),'Compras'!$L9,"") | H47: =IF(AND('Compras'!$H9="Sí",'Compras'!$L9>0),'Compras'!$J9,"") | I47: =IF(AND('Compras'!$H9="Sí",'Compras'!$L9>0),'Compras'!$N9,"") | P47: =IF('Catálogo'!$A47="","",'Catálogo'!$B47) | Q47: =IF('Catálogo'!$A47="","",SUMIF('Ventas'!$D:$D,'Catálogo'!$A47,'Ventas'!$F:$F)) | R47: =IF('Catálogo'!$A47="","",$Q47+ROW()/100000)
A48: =IF(AND('Compras'!$H10="Sí",'Compras'!$L10>0),'Compras'!$A10,"") | B48: =IF(AND('Compras'!$H10="Sí",'Compras'!$L10>0),'Compras'!$C10,"") | E48: =IF(AND('Compras'!$H10="Sí",'Compras'!$L10>0),'Compras'!$G10,"") | G48: =IF(AND('Compras'!$H10="Sí",'Compras'!$L10>0),'Compras'!$L10,"") | H48: =IF(AND('Compras'!$H10="Sí",'Compras'!$L10>0),'Compras'!$J10,"") | I48: =IF(AND('Compras'!$H10="Sí",'Compras'!$L10>0),'Compras'!$N10,"") | P48: =IF('Catálogo'!$A48="","",'Catálogo'!$B48) | Q48: =IF('Catálogo'!$A48="","",SUMIF('Ventas'!$D:$D,'Catálogo'!$A48,'Ventas'!$F:$F)) | R48: =IF('Catálogo'!$A48="","",$Q48+ROW()/100000)
A49: =IF(AND('Compras'!$H11="Sí",'Compras'!$L11>0),'Compras'!$A11,"") | B49: =IF(AND('Compras'!$H11="Sí",'Compras'!$L11>0),'Compras'!$C11,"") | E49: =IF(AND('Compras'!$H11="Sí",'Compras'!$L11>0),'Compras'!$G11,"") | G49: =IF(AND('Compras'!$H11="Sí",'Compras'!$L11>0),'Compras'!$L11,"") | H49: =IF(AND('Compras'!$H11="Sí",'Compras'!$L11>0),'Compras'!$J11,"") | I49: =IF(AND('Compras'!$H11="Sí",'Compras'!$L11>0),'Compras'!$N11,"") | P49: =IF('Catálogo'!$A49="","",'Catálogo'!$B49) | Q49: =IF('Catálogo'!$A49="","",SUMIF('Ventas'!$D:$D,'Catálogo'!$A49,'Ventas'!$F:$F)) | R49: =IF('Catálogo'!$A49="","",$Q49+ROW()/100000)
A50: =IF(AND('Compras'!$H12="Sí",'Compras'!$L12>0),'Compras'!$A12,"") | B50: =IF(AND('Compras'!$H12="Sí",'Compras'!$L12>0),'Compras'!$C12,"") | E50: =IF(AND('Compras'!$H12="Sí",'Compras'!$L12>0),'Compras'!$G12,"") | G50: =IF(AND('Compras'!$H12="Sí",'Compras'!$L12>0),'Compras'!$L12,"") | H50: =IF(AND('Compras'!$H12="Sí",'Compras'!$L12>0),'Compras'!$J12,"") | I50: =IF(AND('Compras'!$H12="Sí",'Compras'!$L12>0),'Compras'!$N12,"") | P50: =IF('Catálogo'!$A50="","",'Catálogo'!$B50) | Q50: =IF('Catálogo'!$A50="","",SUMIF('Ventas'!$D:$D,'Catálogo'!$A50,'Ventas'!$F:$F)) | R50: =IF('Catálogo'!$A50="","",$Q50+ROW()/100000)
A51: =IF(AND('Compras'!$H13="Sí",'Compras'!$L13>0),'Compras'!$A13,"") | B51: =IF(AND('Compras'!$H13="Sí",'Compras'!$L13>0),'Compras'!$C13,"") | E51: =IF(AND('Compras'!$H13="Sí",'Compras'!$L13>0),'Compras'!$G13,"") | G51: =IF(AND('Compras'!$H13="Sí",'Compras'!$L13>0),'Compras'!$L13,"") | H51: =IF(AND('Compras'!$H13="Sí",'Compras'!$L13>0),'Compras'!$J13,"") | I51: =IF(AND('Compras'!$H13="Sí",'Compras'!$L13>0),'Compras'!$N13,"") | P51: =IF('Catálogo'!$A51="","",'Catálogo'!$B51) | Q51: =IF('Catálogo'!$A51="","",SUMIF('Ventas'!$D:$D,'Catálogo'!$A51,'Ventas'!$F:$F)) | R51: =IF('Catálogo'!$A51="","",$Q51+ROW()/100000)
... A54: =IF(AND('Compras'!$H16="Sí",'Compras'!$L16>0),'Compras'!$A16,"") | B54: =IF(AND('Compras'!$H16="Sí",'Compras'!$L16>0),'Compras'!$C16,"") | E54: =IF(AND('Compras'!$H16="Sí",'Compras'!$L16>0),'Compras'!$G16,"") | G54: =IF(AND('Compras'!$H16="Sí",'Compras'!$L16>0),'Compras'!$L16,"") | H54: =IF(AND('Compras'!$H16="Sí",'Compras'!$L16>0),'Compras'!$J16,"") | I54: =IF(AND('Compras'!$H16="Sí",'Compras'!$L16>0),'Compras'!$N16,"") | P54: =IF('Catálogo'!$A54="","",'Catálogo'!$B54) | Q54: =IF('Catálogo'!$A54="","",SUMIF('Ventas'!$D:$D,'Catálogo'!$A54,'Ventas'!$F:$F)) | R54: =IF('Catálogo'!$A54="","",$Q54+ROW()/100000)
P55: =IF('Catálogo'!$A55="","",'Catálogo'!$B55) | Q55: =IF('Catálogo'!$A55="","",SUMIF('Ventas'!$D:$D,'Catálogo'!$A55,'Ventas'!$F:$F)) | R55: =IF('Catálogo'!$A55="","",$Q55+ROW()/100000)
A56: 🤝 PRÉSTAMOS A PERSONAS (dinero de la empresa prestado) | P56: =IF('Catálogo'!$A56="","",'Catálogo'!$B56) | Q56: =IF('Catálogo'!$A56="","",SUMIF('Ventas'!$D:$D,'Catálogo'!$A56,'Ventas'!$F:$F)) | R56: =IF('Catálogo'!$A56="","",$Q56+ROW()/100000)
A57: PRESTADO ACTUALMENTE | D57: PERSONAS QUE ME DEBEN | G57: DÍAS DEL MÁS ANTIGUO SIN PAGAR | P57: =IF('Catálogo'!$A57="","",'Catálogo'!$B57) | Q57: =IF('Catálogo'!$A57="","",SUMIF('Ventas'!$D:$D,'Catálogo'!$A57,'Ventas'!$F:$F)) | R57: =IF('Catálogo'!$A57="","",$Q57+ROW()/100000)
A58: =SUM('Préstamos'!$G:$G) | D58: =COUNTIF('Préstamos'!$H:$H,"Pendiente")+COUNTIF('Préstamos'!$H:$H,"Abono parcial") | G58: =IFERROR(MAX('Préstamos'!$I:$I),0) | P58: =IF('Catálogo'!$A58="","",'Catálogo'!$B58) | Q58: =IF('Catálogo'!$A58="","",SUMIF('Ventas'!$D:$D,'Catálogo'!$A58,'Ventas'!$F:$F)) | R58: =IF('Catálogo'!$A58="","",$Q58+ROW()/100000)
P59: =IF('Catálogo'!$A59="","",'Catálogo'!$B59) | Q59: =IF('Catálogo'!$A59="","",SUMIF('Ventas'!$D:$D,'Catálogo'!$A59,'Ventas'!$F:$F)) | R59: =IF('Catálogo'!$A59="","",$Q59+ROW()/100000)
A60: 📋 QUIÉN ME DEBE — del más antiguo primero (empieza a cobrar por arriba) | P60: =IF('Catálogo'!$A60="","",'Catálogo'!$B60) | Q60: =IF('Catálogo'!$A60="","",SUMIF('Ventas'!$D:$D,'Catálogo'!$A60,'Ventas'!$F:$F)) | R60: =IF('Catálogo'!$A60="","",$Q60+ROW()/100000)
A61: =IFERROR(QUERY('Préstamos'!$A$2:$J$2000,"select B,C,E,F,G,I where G>0 order by I desc label B 'Persona', C 'Teléfono', E 'Prestado', F 'Abonado', G 'Saldo', I 'Días'",0),"Nadie te debe 🎉") | P61: =IF('Catálogo'!$A61="","",'Catálogo'!$B61) | Q61: =IF('Catálogo'!$A61="","",SUMIF('Ventas'!$D:$D,'Catálogo'!$A61,'Ventas'!$F:$F)) | R61: =IF('Catálogo'!$A61="","",$Q61+ROW()/100000)
P62: =IF('Catálogo'!$A62="","",'Catálogo'!$B62) | Q62: =IF('Catálogo'!$A62="","",SUMIF('Ventas'!$D:$D,'Catálogo'!$A62,'Ventas'!$F:$F)) | R62: =IF('Catálogo'!$A62="","",$Q62+ROW()/100000)
P63: =IF('Catálogo'!$A63="","",'Catálogo'!$B63) | Q63: =IF('Catálogo'!$A63="","",SUMIF('Ventas'!$D:$D,'Catálogo'!$A63,'Ventas'!$F:$F)) | R63: =IF('Catálogo'!$A63="","",$Q63+ROW()/100000)
P64: =IF('Catálogo'!$A64="","",'Catálogo'!$B64) | Q64: =IF('Catálogo'!$A64="","",SUMIF('Ventas'!$D:$D,'Catálogo'!$A64,'Ventas'!$F:$F)) | R64: =IF('Catálogo'!$A64="","",$Q64+ROW()/100000)
P65: =IF('Catálogo'!$A65="","",'Catálogo'!$B65) | Q65: =IF('Catálogo'!$A65="","",SUMIF('Ventas'!$D:$D,'Catálogo'!$A65,'Ventas'!$F:$F)) | R65: =IF('Catálogo'!$A65="","",$Q65+ROW()/100000)
P66: =IF('Catálogo'!$A66="","",'Catálogo'!$B66) | Q66: =IF('Catálogo'!$A66="","",SUMIF('Ventas'!$D:$D,'Catálogo'!$A66,'Ventas'!$F:$F)) | R66: =IF('Catálogo'!$A66="","",$Q66+ROW()/100000)
P67: =IF('Catálogo'!$A67="","",'Catálogo'!$B67) | Q67: =IF('Catálogo'!$A67="","",SUMIF('Ventas'!$D:$D,'Catálogo'!$A67,'Ventas'!$F:$F)) | R67: =IF('Catálogo'!$A67="","",$Q67+ROW()/100000)
P68: =IF('Catálogo'!$A68="","",'Catálogo'!$B68) | Q68: =IF('Catálogo'!$A68="","",SUMIF('Ventas'!$D:$D,'Catálogo'!$A68,'Ventas'!$F:$F)) | R68: =IF('Catálogo'!$A68="","",$Q68+ROW()/100000)
P69: =IF('Catálogo'!$A69="","",'Catálogo'!$B69) | Q69: =IF('Catálogo'!$A69="","",SUMIF('Ventas'!$D:$D,'Catálogo'!$A69,'Ventas'!$F:$F)) | R69: =IF('Catálogo'!$A69="","",$Q69+ROW()/100000)
P70: =IF('Catálogo'!$A70="","",'Catálogo'!$B70) | Q70: =IF('Catálogo'!$A70="","",SUMIF('Ventas'!$D:$D,'Catálogo'!$A70,'Ventas'!$F:$F)) | R70: =IF('Catálogo'!$A70="","",$Q70+ROW()/100000)
P71: =IF('Catálogo'!$A71="","",'Catálogo'!$B71) | Q71: =IF('Catálogo'!$A71="","",SUMIF('Ventas'!$D:$D,'Catálogo'!$A71,'Ventas'!$F:$F)) | R71: =IF('Catálogo'!$A71="","",$Q71+ROW()/100000)
P72: =IF('Catálogo'!$A72="","",'Catálogo'!$B72) | Q72: =IF('Catálogo'!$A72="","",SUMIF('Ventas'!$D:$D,'Catálogo'!$A72,'Ventas'!$F:$F)) | R72: =IF('Catálogo'!$A72="","",$Q72+ROW()/100000)
P73: =IF('Catálogo'!$A73="","",'Catálogo'!$B73) | Q73: =IF('Catálogo'!$A73="","",SUMIF('Ventas'!$D:$D,'Catálogo'!$A73,'Ventas'!$F:$F)) | R73: =IF('Catálogo'!$A73="","",$Q73+ROW()/100000)
... P201: =IF('Catálogo'!$A201="","",'Catálogo'!$B201) | Q201: =IF('Catálogo'!$A201="","",SUMIF('Ventas'!$D:$D,'Catálogo'!$A201,'Ventas'!$F:$F)) | R201: =IF('Catálogo'!$A201="","",$Q201+ROW()/100000)

Sheet Catálogo
A1: Código | B1: Nombre | C1: Categoría | D1: Estado | E1: Stock Mínimo | F1: Costo Promedio | G1: Stock Casa | H1: Stock Mercado Libre | I1: Stock Total | J1: Valor Inventario | K1: Estado Stock | L1: IVA % | M1: URL Imagen | N1: Precio Detal | O1: Precio Mayor | P1: _rank | Q1: _key | R1: Medidas (ej. 30x40) | S1: _orden | T1: _rankAll | U1: _keyAll | V1: Fecha 1ª Compra | W1: Días en Bodega | X1: Vendidas (total) | Y1: Reabastecer
F2: =IF($A2="","",IFERROR(SUMIF('Compras'!$B:$B,$A2,'Compras'!$F:$F)/SUMIF('Compras'!$B:$B,$A2,'Compras'!$D:$D),0)) | G2: =IF($A2="","",SUMIF('Compras'!$B:$B,$A2,'Compras'!$D:$D)+SUMIF('Traslados'!$H:$H,$A2&"|Casa",'Traslados'!$D:$D)-SUMIF('Traslados'!$G:$G,$A2&"|Casa",'Traslados'!$D:$D)-SUMIF('Ventas'!$M:$M,$A2&"|Casa",'Ventas'!$F:$F)+SUMIF('Ajustes'!$H:$H,$A2&"|Casa",'Ajustes'!$D:$D)) | H2: =IF($A2="","",SUMIF('Traslados'!$H:$H,$A2&"|Mercado Libre",'Traslados'!$D:$D)-SUMIF('Traslados'!$G:$G,$A2&"|Mercado Libre",'Traslados'!$D:$D)-SUMIF('Ventas'!$M:$M,$A2&"|Mercado Libre",'Ventas'!$F:$F)+SUMIF('Ajustes'!$H:$H,$A2&"|Mercado Libre",'Ajustes'!$D:$D)) | I2: =IF($A2="","",$G2+$H2) | J2: =IF($A2="","",$I2*$F2) | K2: =IF($A2="","",IF($I2<=0,"Agotado",IF($I2<=$E2,"Stock bajo","Disponible"))) | L2: =IF($A2="","",IFERROR(VLOOKUP($C2,'Config'!$D$2:$E$30,2,FALSE),0)) | P2: =IF(OR($A2="",$D2<>"Activo"),"",SUMPRODUCT(($C$2:$C$201=$C2)*($D$2:$D$201="Activo")*(($S$2:$S$201<$S2)+(($S$2:$S$201=$S2)*($B$2:$B$201<$B2))))+1) | Q2: =IF($P2="","",$C2&"|"&$P2) | S2: =IF($A2="","",IFERROR(VALUE(TRIM(LEFT($R2,FIND("x",LOWER($R2))-1)))*VALUE(TRIM(MID($R2,FIND("x",LOWER($R2))+1,20))),0)) | T2: =IF(OR($A2="",$D2<>"Activo"),"",SUMPRODUCT(($D$2:$D$201="Activo")*(($C$2:$C$201<$C2)+(($C$2:$C$201=$C2)*($S$2:$S$201<$S2))+(($C$2:$C$201=$C2)*($S$2:$S$201=$S2)*($B$2:$B$201<$B2))))+1) | U2: =IF($T2="","","TODAS|"&$T2) | V2: =IF($A2="","",IFERROR(IF(COUNTIF('Compras'!$B:$B,$A2)=0,"",MINIFS('Compras'!$A:$A,'Compras'!$B:$B,$A2)),"")) | W2: =IF(OR($A2="",$V2=""),"",TODAY()-$V2) | X2: =IF($A2="","",SUMIF('Ventas'!$D:$D,$A2,'Ventas'!$F:$F)) | Y2: =IF($A2="","",IF(AND($X2>=3,$W2<>"",$W2<=15),"🔥 Se vende rápido — REABASTECE",IF($K2="Agotado","🔴 Agotado — reabastece",IF($K2="Stock bajo","🟠 Stock bajo","✅ Ok"))))
F3: =IF($A3="","",IFERROR(SUMIF('Compras'!$B:$B,$A3,'Compras'!$F:$F)/SUMIF('Compras'!$B:$B,$A3,'Compras'!$D:$D),0)) | G3: =IF($A3="","",SUMIF('Compras'!$B:$B,$A3,'Compras'!$D:$D)+SUMIF('Traslados'!$H:$H,$A3&"|Casa",'Traslados'!$D:$D)-SUMIF('Traslados'!$G:$G,$A3&"|Casa",'Traslados'!$D:$D)-SUMIF('Ventas'!$M:$M,$A3&"|Casa",'Ventas'!$F:$F)+SUMIF('Ajustes'!$H:$H,$A3&"|Casa",'Ajustes'!$D:$D)) | H3: =IF($A3="","",SUMIF('Traslados'!$H:$H,$A3&"|Mercado Libre",'Traslados'!$D:$D)-SUMIF('Traslados'!$G:$G,$A3&"|Mercado Libre",'Traslados'!$D:$D)-SUMIF('Ventas'!$M:$M,$A3&"|Mercado Libre",'Ventas'!$F:$F)+SUMIF('Ajustes'!$H:$H,$A3&"|Mercado Libre",'Ajustes'!$D:$D)) | I3: =IF($A3="","",$G3+$H3) | J3: =IF($A3="","",$I3*$F3) | K3: =IF($A3="","",IF($I3<=0,"Agotado",IF($I3<=$E3,"Stock bajo","Disponible"))) | L3: =IF($A3="","",IFERROR(VLOOKUP($C3,'Config'!$D$2:$E$30,2,FALSE),0)) | P3: =IF(OR($A3="",$D3<>"Activo"),"",SUMPRODUCT(($C$2:$C$201=$C3)*($D$2:$D$201="Activo")*(($S$2:$S$201<$S3)+(($S$2:$S$201=$S3)*($B$2:$B$201<$B3))))+1) | Q3: =IF($P3="","",$C3&"|"&$P3) | S3: =IF($A3="","",IFERROR(VALUE(TRIM(LEFT($R3,FIND("x",LOWER($R3))-1)))*VALUE(TRIM(MID($R3,FIND("x",LOWER($R3))+1,20))),0)) | T3: =IF(OR($A3="",$D3<>"Activo"),"",SUMPRODUCT(($D$2:$D$201="Activo")*(($C$2:$C$201<$C3)+(($C$2:$C$201=$C3)*($S$2:$S$201<$S3))+(($C$2:$C$201=$C3)*($S$2:$S$201=$S3)*($B$2:$B$201<$B3))))+1) | U3: =IF($T3="","","TODAS|"&$T3) | V3: =IF($A3="","",IFERROR(IF(COUNTIF('Compras'!$B:$B,$A3)=0,"",MINIFS('Compras'!$A:$A,'Compras'!$B:$B,$A3)),"")) | W3: =IF(OR($A3="",$V3=""),"",TODAY()-$V3) | X3: =IF($A3="","",SUMIF('Ventas'!$D:$D,$A3,'Ventas'!$F:$F)) | Y3: =IF($A3="","",IF(AND($X3>=3,$W3<>"",$W3<=15),"🔥 Se vende rápido — REABASTECE",IF($K3="Agotado","🔴 Agotado — reabastece",IF($K3="Stock bajo","🟠 Stock bajo","✅ Ok"))))
F4: =IF($A4="","",IFERROR(SUMIF('Compras'!$B:$B,$A4,'Compras'!$F:$F)/SUMIF('Compras'!$B:$B,$A4,'Compras'!$D:$D),0)) | G4: =IF($A4="","",SUMIF('Compras'!$B:$B,$A4,'Compras'!$D:$D)+SUMIF('Traslados'!$H:$H,$A4&"|Casa",'Traslados'!$D:$D)-SUMIF('Traslados'!$G:$G,$A4&"|Casa",'Traslados'!$D:$D)-SUMIF('Ventas'!$M:$M,$A4&"|Casa",'Ventas'!$F:$F)+SUMIF('Ajustes'!$H:$H,$A4&"|Casa",'Ajustes'!$D:$D)) | H4: =IF($A4="","",SUMIF('Traslados'!$H:$H,$A4&"|Mercado Libre",'Traslados'!$D:$D)-SUMIF('Traslados'!$G:$G,$A4&"|Mercado Libre",'Traslados'!$D:$D)-SUMIF('Ventas'!$M:$M,$A4&"|Mercado Libre",'Ventas'!$F:$F)+SUMIF('Ajustes'!$H:$H,$A4&"|Mercado Libre",'Ajustes'!$D:$D)) | I4: =IF($A4="","",$G4+$H4) | J4: =IF($A4="","",$I4*$F4) | K4: =IF($A4="","",IF($I4<=0,"Agotado",IF($I4<=$E4,"Stock bajo","Disponible"))) | L4: =IF($A4="","",IFERROR(VLOOKUP($C4,'Config'!$D$2:$E$30,2,FALSE),0)) | P4: =IF(OR($A4="",$D4<>"Activo"),"",SUMPRODUCT(($C$2:$C$201=$C4)*($D$2:$D$201="Activo")*(($S$2:$S$201<$S4)+(($S$2:$S$201=$S4)*($B$2:$B$201<$B4))))+1) | Q4: =IF($P4="","",$C4&"|"&$P4) | S4: =IF($A4="","",IFERROR(VALUE(TRIM(LEFT($R4,FIND("x",LOWER($R4))-1)))*VALUE(TRIM(MID($R4,FIND("x",LOWER($R4))+1,20))),0)) | T4: =IF(OR($A4="",$D4<>"Activo"),"",SUMPRODUCT(($D$2:$D$201="Activo")*(($C$2:$C$201<$C4)+(($C$2:$C$201=$C4)*($S$2:$S$201<$S4))+(($C$2:$C$201=$C4)*($S$2:$S$201=$S4)*($B$2:$B$201<$B4))))+1) | U4: =IF($T4="","","TODAS|"&$T4) | V4: =IF($A4="","",IFERROR(IF(COUNTIF('Compras'!$B:$B,$A4)=0,"",MINIFS('Compras'!$A:$A,'Compras'!$B:$B,$A4)),"")) | W4: =IF(OR($A4="",$V4=""),"",TODAY()-$V4) | X4: =IF($A4="","",SUMIF('Ventas'!$D:$D,$A4,'Ventas'!$F:$F)) | Y4: =IF($A4="","",IF(AND($X4>=3,$W4<>"",$W4<=15),"🔥 Se vende rápido — REABASTECE",IF($K4="Agotado","🔴 Agotado — reabastece",IF($K4="Stock bajo","🟠 Stock bajo","✅ Ok"))))
F5: =IF($A5="","",IFERROR(SUMIF('Compras'!$B:$B,$A5,'Compras'!$F:$F)/SUMIF('Compras'!$B:$B,$A5,'Compras'!$D:$D),0)) | G5: =IF($A5="","",SUMIF('Compras'!$B:$B,$A5,'Compras'!$D:$D)+SUMIF('Traslados'!$H:$H,$A5&"|Casa",'Traslados'!$D:$D)-SUMIF('Traslados'!$G:$G,$A5&"|Casa",'Traslados'!$D:$D)-SUMIF('Ventas'!$M:$M,$A5&"|Casa",'Ventas'!$F:$F)+SUMIF('Ajustes'!$H:$H,$A5&"|Casa",'Ajustes'!$D:$D)) | H5: =IF($A5="","",SUMIF('Traslados'!$H:$H,$A5&"|Mercado Libre",'Traslados'!$D:$D)-SUMIF('Traslados'!$G:$G,$A5&"|Mercado Libre",'Traslados'!$D:$D)-SUMIF('Ventas'!$M:$M,$A5&"|Mercado Libre",'Ventas'!$F:$F)+SUMIF('Ajustes'!$H:$H,$A5&"|Mercado Libre",'Ajustes'!$D:$D)) | I5: =IF($A5="","",$G5+$H5) | J5: =IF($A5="","",$I5*$F5) | K5: =IF($A5="","",IF($I5<=0,"Agotado",IF($I5<=$E5,"Stock bajo","Disponible"))) | L5: =IF($A5="","",IFERROR(VLOOKUP($C5,'Config'!$D$2:$E$30,2,FALSE),0)) | P5: =IF(OR($A5="",$D5<>"Activo"),"",SUMPRODUCT(($C$2:$C$201=$C5)*($D$2:$D$201="Activo")*(($S$2:$S$201<$S5)+(($S$2:$S$201=$S5)*($B$2:$B$201<$B5))))+1) | Q5: =IF($P5="","",$C5&"|"&$P5) | S5: =IF($A5="","",IFERROR(VALUE(TRIM(LEFT($R5,FIND("x",LOWER($R5))-1)))*VALUE(TRIM(MID($R5,FIND("x",LOWER($R5))+1,20))),0)) | T5: =IF(OR($A5="",$D5<>"Activo"),"",SUMPRODUCT(($D$2:$D$201="Activo")*(($C$2:$C$201<$C5)+(($C$2:$C$201=$C5)*($S$2:$S$201<$S5))+(($C$2:$C$201=$C5)*($S$2:$S$201=$S5)*($B$2:$B$201<$B5))))+1) | U5: =IF($T5="","","TODAS|"&$T5) | V5: =IF($A5="","",IFERROR(IF(COUNTIF('Compras'!$B:$B,$A5)=0,"",MINIFS('Compras'!$A:$A,'Compras'!$B:$B,$A5)),"")) | W5: =IF(OR($A5="",$V5=""),"",TODAY()-$V5) | X5: =IF($A5="","",SUMIF('Ventas'!$D:$D,$A5,'Ventas'!$F:$F)) | Y5: =IF($A5="","",IF(AND($X5>=3,$W5<>"",$W5<=15),"🔥 Se vende rápido — REABASTECE",IF($K5="Agotado","🔴 Agotado — reabastece",IF($K5="Stock bajo","🟠 Stock bajo","✅ Ok"))))
F6: =IF($A6="","",IFERROR(SUMIF('Compras'!$B:$B,$A6,'Compras'!$F:$F)/SUMIF('Compras'!$B:$B,$A6,'Compras'!$D:$D),0)) | G6: =IF($A6="","",SUMIF('Compras'!$B:$B,$A6,'Compras'!$D:$D)+SUMIF('Traslados'!$H:$H,$A6&"|Casa",'Traslados'!$D:$D)-SUMIF('Traslados'!$G:$G,$A6&"|Casa",'Traslados'!$D:$D)-SUMIF('Ventas'!$M:$M,$A6&"|Casa",'Ventas'!$F:$F)+SUMIF('Ajustes'!$H:$H,$A6&"|Casa",'Ajustes'!$D:$D)) | H6: =IF($A6="","",SUMIF('Traslados'!$H:$H,$A6&"|Mercado Libre",'Traslados'!$D:$D)-SUMIF('Traslados'!$G:$G,$A6&"|Mercado Libre",'Traslados'!$D:$D)-SUMIF('Ventas'!$M:$M,$A6&"|Mercado Libre",'Ventas'!$F:$F)+SUMIF('Ajustes'!$H:$H,$A6&"|Mercado Libre",'Ajustes'!$D:$D)) | I6: =IF($A6="","",$G6+$H6) | J6: =IF($A6="","",$I6*$F6) | K6: =IF($A6="","",IF($I6<=0,"Agotado",IF($I6<=$E6,"Stock bajo","Disponible"))) | L6: =IF($A6="","",IFERROR(VLOOKUP($C6,'Config'!$D$2:$E$30,2,FALSE),0)) | P6: =IF(OR($A6="",$D6<>"Activo"),"",SUMPRODUCT(($C$2:$C$201=$C6)*($D$2:$D$201="Activo")*(($S$2:$S$201<$S6)+(($S$2:$S$201=$S6)*($B$2:$B$201<$B6))))+1) | Q6: =IF($P6="","",$C6&"|"&$P6) | S6: =IF($A6="","",IFERROR(VALUE(TRIM(LEFT($R6,FIND("x",LOWER($R6))-1)))*VALUE(TRIM(MID($R6,FIND("x",LOWER($R6))+1,20))),0)) | T6: =IF(OR($A6="",$D6<>"Activo"),"",SUMPRODUCT(($D$2:$D$201="Activo")*(($C$2:$C$201<$C6)+(($C$2:$C$201=$C6)*($S$2:$S$201<$S6))+(($C$2:$C$201=$C6)*($S$2:$S$201=$S6)*($B$2:$B$201<$B6))))+1) | U6: =IF($T6="","","TODAS|"&$T6) | V6: =IF($A6="","",IFERROR(IF(COUNTIF('Compras'!$B:$B,$A6)=0,"",MINIFS('Compras'!$A:$A,'Compras'!$B:$B,$A6)),"")) | W6: =IF(OR($A6="",$V6=""),"",TODAY()-$V6) | X6: =IF($A6="","",SUMIF('Ventas'!$D:$D,$A6,'Ventas'!$F:$F)) | Y6: =IF($A6="","",IF(AND($X6>=3,$W6<>"",$W6<=15),"🔥 Se vende rápido — REABASTECE",IF($K6="Agotado","🔴 Agotado — reabastece",IF($K6="Stock bajo","🟠 Stock bajo","✅ Ok"))))
F7: =IF($A7="","",IFERROR(SUMIF('Compras'!$B:$B,$A7,'Compras'!$F:$F)/SUMIF('Compras'!$B:$B,$A7,'Compras'!$D:$D),0)) | G7: =IF($A7="","",SUMIF('Compras'!$B:$B,$A7,'Compras'!$D:$D)+SUMIF('Traslados'!$H:$H,$A7&"|Casa",'Traslados'!$D:$D)-SUMIF('Traslados'!$G:$G,$A7&"|Casa",'Traslados'!$D:$D)-SUMIF('Ventas'!$M:$M,$A7&"|Casa",'Ventas'!$F:$F)+SUMIF('Ajustes'!$H:$H,$A7&"|Casa",'Ajustes'!$D:$D)) | H7: =IF($A7="","",SUMIF('Traslados'!$H:$H,$A7&"|Mercado Libre",'Traslados'!$D:$D)-SUMIF('Traslados'!$G:$G,$A7&"|Mercado Libre",'Traslados'!$D:$D)-SUMIF('Ventas'!$M:$M,$A7&"|Mercado Libre",'Ventas'!$F:$F)+SUMIF('Ajustes'!$H:$H,$A7&"|Mercado Libre",'Ajustes'!$D:$D)) | I7: =IF($A7="","",$G7+$H7) | J7: =IF($A7="","",$I7*$F7) | K7: =IF($A7="","",IF($I7<=0,"Agotado",IF($I7<=$E7,"Stock bajo","Disponible"))) | L7: =IF($A7="","",IFERROR(VLOOKUP($C7,'Config'!$D$2:$E$30,2,FALSE),0)) | P7: =IF(OR($A7="",$D7<>"Activo"),"",SUMPRODUCT(($C$2:$C$201=$C7)*($D$2:$D$201="Activo")*(($S$2:$S$201<$S7)+(($S$2:$S$201=$S7)*($B$2:$B$201<$B7))))+1) | Q7: =IF($P7="","",$C7&"|"&$P7) | S7: =IF($A7="","",IFERROR(VALUE(TRIM(LEFT($R7,FIND("x",LOWER($R7))-1)))*VALUE(TRIM(MID($R7,FIND("x",LOWER($R7))+1,20))),0)) | T7: =IF(OR($A7="",$D7<>"Activo"),"",SUMPRODUCT(($D$2:$D$201="Activo")*(($C$2:$C$201<$C7)+(($C$2:$C$201=$C7)*($S$2:$S$201<$S7))+(($C$2:$C$201=$C7)*($S$2:$S$201=$S7)*($B$2:$B$201<$B7))))+1) | U7: =IF($T7="","","TODAS|"&$T7) | V7: =IF($A7="","",IFERROR(IF(COUNTIF('Compras'!$B:$B,$A7)=0,"",MINIFS('Compras'!$A:$A,'Compras'!$B:$B,$A7)),"")) | W7: =IF(OR($A7="",$V7=""),"",TODAY()-$V7) | X7: =IF($A7="","",SUMIF('Ventas'!$D:$D,$A7,'Ventas'!$F:$F)) | Y7: =IF($A7="","",IF(AND($X7>=3,$W7<>"",$W7<=15),"🔥 Se vende rápido — REABASTECE",IF($K7="Agotado","🔴 Agotado — reabastece",IF($K7="Stock bajo","🟠 Stock bajo","✅ Ok"))))
F8: =IF($A8="","",IFERROR(SUMIF('Compras'!$B:$B,$A8,'Compras'!$F:$F)/SUMIF('Compras'!$B:$B,$A8,'Compras'!$D:$D),0)) | G8: =IF($A8="","",SUMIF('Compras'!$B:$B,$A8,'Compras'!$D:$D)+SUMIF('Traslados'!$H:$H,$A8&"|Casa",'Traslados'!$D:$D)-SUMIF('Traslados'!$G:$G,$A8&"|Casa",'Traslados'!$D:$D)-SUMIF('Ventas'!$M:$M,$A8&"|Casa",'Ventas'!$F:$F)+SUMIF('Ajustes'!$H:$H,$A8&"|Casa",'Ajustes'!$D:$D)) | H8: =IF($A8="","",SUMIF('Traslados'!$H:$H,$A8&"|Mercado Libre",'Traslados'!$D:$D)-SUMIF('Traslados'!$G:$G,$A8&"|Mercado Libre",'Traslados'!$D:$D)-SUMIF('Ventas'!$M:$M,$A8&"|Mercado Libre",'Ventas'!$F:$F)+SUMIF('Ajustes'!$H:$H,$A8&"|Mercado Libre",'Ajustes'!$D:$D)) | I8: =IF($A8="","",$G8+$H8) | J8: =IF($A8="","",$I8*$F8) | K8: =IF($A8="","",IF($I8<=0,"Agotado",IF($I8<=$E8,"Stock bajo","Disponible"))) | L8: =IF($A8="","",IFERROR(VLOOKUP($C8,'Config'!$D$2:$E$30,2,FALSE),0)) | P8: =IF(OR($A8="",$D8<>"Activo"),"",SUMPRODUCT(($C$2:$C$201=$C8)*($D$2:$D$201="Activo")*(($S$2:$S$201<$S8)+(($S$2:$S$201=$S8)*($B$2:$B$201<$B8))))+1) | Q8: =IF($P8="","",$C8&"|"&$P8) | S8: =IF($A8="","",IFERROR(VALUE(TRIM(LEFT($R8,FIND("x",LOWER($R8))-1)))*VALUE(TRIM(MID($R8,FIND("x",LOWER($R8))+1,20))),0)) | T8: =IF(OR($A8="",$D8<>"Activo"),"",SUMPRODUCT(($D$2:$D$201="Activo")*(($C$2:$C$201<$C8)+(($C$2:$C$201=$C8)*($S$2:$S$201<$S8))+(($C$2:$C$201=$C8)*($S$2:$S$201=$S8)*($B$2:$B$201<$B8))))+1) | U8: =IF($T8="","","TODAS|"&$T8) | V8: =IF($A8="","",IFERROR(IF(COUNTIF('Compras'!$B:$B,$A8)=0,"",MINIFS('Compras'!$A:$A,'Compras'!$B:$B,$A8)),"")) | W8: =IF(OR($A8="",$V8=""),"",TODAY()-$V8) | X8: =IF($A8="","",SUMIF('Ventas'!$D:$D,$A8,'Ventas'!$F:$F)) | Y8: =IF($A8="","",IF(AND($X8>=3,$W8<>"",$W8<=15),"🔥 Se vende rápido — REABASTECE",IF($K8="Agotado","🔴 Agotado — reabastece",IF($K8="Stock bajo","🟠 Stock bajo","✅ Ok"))))
F9: =IF($A9="","",IFERROR(SUMIF('Compras'!$B:$B,$A9,'Compras'!$F:$F)/SUMIF('Compras'!$B:$B,$A9,'Compras'!$D:$D),0)) | G9: =IF($A9="","",SUMIF('Compras'!$B:$B,$A9,'Compras'!$D:$D)+SUMIF('Traslados'!$H:$H,$A9&"|Casa",'Traslados'!$D:$D)-SUMIF('Traslados'!$G:$G,$A9&"|Casa",'Traslados'!$D:$D)-SUMIF('Ventas'!$M:$M,$A9&"|Casa",'Ventas'!$F:$F)+SUMIF('Ajustes'!$H:$H,$A9&"|Casa",'Ajustes'!$D:$D)) | H9: =IF($A9="","",SUMIF('Traslados'!$H:$H,$A9&"|Mercado Libre",'Traslados'!$D:$D)-SUMIF('Traslados'!$G:$G,$A9&"|Mercado Libre",'Traslados'!$D:$D)-SUMIF('Ventas'!$M:$M,$A9&"|Mercado Libre",'Ventas'!$F:$F)+SUMIF('Ajustes'!$H:$H,$A9&"|Mercado Libre",'Ajustes'!$D:$D)) | I9: =IF($A9="","",$G9+$H9) | J9: =IF($A9="","",$I9*$F9) | K9: =IF($A9="","",IF($I9<=0,"Agotado",IF($I9<=$E9,"Stock bajo","Disponible"))) | L9: =IF($A9="","",IFERROR(VLOOKUP($C9,'Config'!$D$2:$E$30,2,FALSE),0)) | P9: =IF(OR($A9="",$D9<>"Activo"),"",SUMPRODUCT(($C$2:$C$201=$C9)*($D$2:$D$201="Activo")*(($S$2:$S$201<$S9)+(($S$2:$S$201=$S9)*($B$2:$B$201<$B9))))+1) | Q9: =IF($P9="","",$C9&"|"&$P9) | S9: =IF($A9="","",IFERROR(VALUE(TRIM(LEFT($R9,FIND("x",LOWER($R9))-1)))*VALUE(TRIM(MID($R9,FIND("x",LOWER($R9))+1,20))),0)) | T9: =IF(OR($A9="",$D9<>"Activo"),"",SUMPRODUCT(($D$2:$D$201="Activo")*(($C$2:$C$201<$C9)+(($C$2:$C$201=$C9)*($S$2:$S$201<$S9))+(($C$2:$C$201=$C9)*($S$2:$S$201=$S9)*($B$2:$B$201<$B9))))+1) | U9: =IF($T9="","","TODAS|"&$T9) | V9: =IF($A9="","",IFERROR(IF(COUNTIF('Compras'!$B:$B,$A9)=0,"",MINIFS('Compras'!$A:$A,'Compras'!$B:$B,$A9)),"")) | W9: =IF(OR($A9="",$V9=""),"",TODAY()-$V9) | X9: =IF($A9="","",SUMIF('Ventas'!$D:$D,$A9,'Ventas'!$F:$F)) | Y9: =IF($A9="","",IF(AND($X9>=3,$W9<>"",$W9<=15),"🔥 Se vende rápido — REABASTECE",IF($K9="Agotado","🔴 Agotado — reabastece",IF($K9="Stock bajo","🟠 Stock bajo","✅ Ok"))))
F10: =IF($A10="","",IFERROR(SUMIF('Compras'!$B:$B,$A10,'Compras'!$F:$F)/SUMIF('Compras'!$B:$B,$A10,'Compras'!$D:$D),0)) | G10: =IF($A10="","",SUMIF('Compras'!$B:$B,$A10,'Compras'!$D:$D)+SUMIF('Traslados'!$H:$H,$A10&"|Casa",'Traslados'!$D:$D)-SUMIF('Traslados'!$G:$G,$A10&"|Casa",'Traslados'!$D:$D)-SUMIF('Ventas'!$M:$M,$A10&"|Casa",'Ventas'!$F:$F)+SUMIF('Ajustes'!$H:$H,$A10&"|Casa",'Ajustes'!$D:$D)) | H10: =IF($A10="","",SUMIF('Traslados'!$H:$H,$A10&"|Mercado Libre",'Traslados'!$D:$D)-SUMIF('Traslados'!$G:$G,$A10&"|Mercado Libre",'Traslados'!$D:$D)-SUMIF('Ventas'!$M:$M,$A10&"|Mercado Libre",'Ventas'!$F:$F)+SUMIF('Ajustes'!$H:$H,$A10&"|Mercado Libre",'Ajustes'!$D:$D)) | I10: =IF($A10="","",$G10+$H10) | J10: =IF($A10="","",$I10*$F10) | K10: =IF($A10="","",IF($I10<=0,"Agotado",IF($I10<=$E10,"Stock bajo","Disponible"))) | L10: =IF($A10="","",IFERROR(VLOOKUP($C10,'Config'!$D$2:$E$30,2,FALSE),0)) | P10: =IF(OR($A10="",$D10<>"Activo"),"",SUMPRODUCT(($C$2:$C$201=$C10)*($D$2:$D$201="Activo")*(($S$2:$S$201<$S10)+(($S$2:$S$201=$S10)*($B$2:$B$201<$B10))))+1) | Q10: =IF($P10="","",$C10&"|"&$P10) | S10: =IF($A10="","",IFERROR(VALUE(TRIM(LEFT($R10,FIND("x",LOWER($R10))-1)))*VALUE(TRIM(MID($R10,FIND("x",LOWER($R10))+1,20))),0)) | T10: =IF(OR($A10="",$D10<>"Activo"),"",SUMPRODUCT(($D$2:$D$201="Activo")*(($C$2:$C$201<$C10)+(($C$2:$C$201=$C10)*($S$2:$S$201<$S10))+(($C$2:$C$201=$C10)*($S$2:$S$201=$S10)*($B$2:$B$201<$B10))))+1) | U10: =IF($T10="","","TODAS|"&$T10) | V10: =IF($A10="","",IFERROR(IF(COUNTIF('Compras'!$B:$B,$A10)=0,"",MINIFS('Compras'!$A:$A,'Compras'!$B:$B,$A10)),"")) | W10: =IF(OR($A10="",$V10=""),"",TODAY()-$V10) | X10: =IF($A10="","",SUMIF('Ventas'!$D:$D,$A10,'Ventas'!$F:$F)) | Y10: =IF($A10="","",IF(AND($X10>=3,$W10<>"",$W10<=15),"🔥 Se vende rápido — REABASTECE",IF($K10="Agotado","🔴 Agotado — reabastece",IF($K10="Stock bajo","🟠 Stock bajo","✅ Ok"))))
F11: =IF($A11="","",IFERROR(SUMIF('Compras'!$B:$B,$A11,'Compras'!$F:$F)/SUMIF('Compras'!$B:$B,$A11,'Compras'!$D:$D),0)) | G11: =IF($A11="","",SUMIF('Compras'!$B:$B,$A11,'Compras'!$D:$D)+SUMIF('Traslados'!$H:$H,$A11&"|Casa",'Traslados'!$D:$D)-SUMIF('Traslados'!$G:$G,$A11&"|Casa",'Traslados'!$D:$D)-SUMIF('Ventas'!$M:$M,$A11&"|Casa",'Ventas'!$F:$F)+SUMIF('Ajustes'!$H:$H,$A11&"|Casa",'Ajustes'!$D:$D)) | H11: =IF($A11="","",SUMIF('Traslados'!$H:$H,$A11&"|Mercado Libre",'Traslados'!$D:$D)-SUMIF('Traslados'!$G:$G,$A11&"|Mercado Libre",'Traslados'!$D:$D)-SUMIF('Ventas'!$M:$M,$A11&"|Mercado Libre",'Ventas'!$F:$F)+SUMIF('Ajustes'!$H:$H,$A11&"|Mercado Libre",'Ajustes'!$D:$D)) | I11: =IF($A11="","",$G11+$H11) | J11: =IF($A11="","",$I11*$F11) | K11: =IF($A11="","",IF($I11<=0,"Agotado",IF($I11<=$E11,"Stock bajo","Disponible"))) | L11: =IF($A11="","",IFERROR(VLOOKUP($C11,'Config'!$D$2:$E$30,2,FALSE),0)) | P11: =IF(OR($A11="",$D11<>"Activo"),"",SUMPRODUCT(($C$2:$C$201=$C11)*($D$2:$D$201="Activo")*(($S$2:$S$201<$S11)+(($S$2:$S$201=$S11)*($B$2:$B$201<$B11))))+1) | Q11: =IF($P11="","",$C11&"|"&$P11) | S11: =IF($A11="","",IFERROR(VALUE(TRIM(LEFT($R11,FIND("x",LOWER($R11))-1)))*VALUE(TRIM(MID($R11,FIND("x",LOWER($R11))+1,20))),0)) | T11: =IF(OR($A11="",$D11<>"Activo"),"",SUMPRODUCT(($D$2:$D$201="Activo")*(($C$2:$C$201<$C11)+(($C$2:$C$201=$C11)*($S$2:$S$201<$S11))+(($C$2:$C$201=$C11)*($S$2:$S$201=$S11)*($B$2:$B$201<$B11))))+1) | U11: =IF($T11="","","TODAS|"&$T11) | V11: =IF($A11="","",IFERROR(IF(COUNTIF('Compras'!$B:$B,$A11)=0,"",MINIFS('Compras'!$A:$A,'Compras'!$B:$B,$A11)),"")) | W11: =IF(OR($A11="",$V11=""),"",TODAY()-$V11) | X11: =IF($A11="","",SUMIF('Ventas'!$D:$D,$A11,'Ventas'!$F:$F)) | Y11: =IF($A11="","",IF(AND($X11>=3,$W11<>"",$W11<=15),"🔥 Se vende rápido — REABASTECE",IF($K11="Agotado","🔴 Agotado — reabastece",IF($K11="Stock bajo","🟠 Stock bajo","✅ Ok"))))
F12: =IF($A12="","",IFERROR(SUMIF('Compras'!$B:$B,$A12,'Compras'!$F:$F)/SUMIF('Compras'!$B:$B,$A12,'Compras'!$D:$D),0)) | G12: =IF($A12="","",SUMIF('Compras'!$B:$B,$A12,'Compras'!$D:$D)+SUMIF('Traslados'!$H:$H,$A12&"|Casa",'Traslados'!$D:$D)-SUMIF('Traslados'!$G:$G,$A12&"|Casa",'Traslados'!$D:$D)-SUMIF('Ventas'!$M:$M,$A12&"|Casa",'Ventas'!$F:$F)+SUMIF('Ajustes'!$H:$H,$A12&"|Casa",'Ajustes'!$D:$D)) | H12: =IF($A12="","",SUMIF('Traslados'!$H:$H,$A12&"|Mercado Libre",'Traslados'!$D:$D)-SUMIF('Traslados'!$G:$G,$A12&"|Mercado Libre",'Traslados'!$D:$D)-SUMIF('Ventas'!$M:$M,$A12&"|Mercado Libre",'Ventas'!$F:$F)+SUMIF('Ajustes'!$H:$H,$A12&"|Mercado Libre",'Ajustes'!$D:$D)) | I12: =IF($A12="","",$G12+$H12) | J12: =IF($A12="","",$I12*$F12) | K12: =IF($A12="","",IF($I12<=0,"Agotado",IF($I12<=$E12,"Stock bajo","Disponible"))) | L12: =IF($A12="","",IFERROR(VLOOKUP($C12,'Config'!$D$2:$E$30,2,FALSE),0)) | P12: =IF(OR($A12="",$D12<>"Activo"),"",SUMPRODUCT(($C$2:$C$201=$C12)*($D$2:$D$201="Activo")*(($S$2:$S$201<$S12)+(($S$2:$S$201=$S12)*($B$2:$B$201<$B12))))+1) | Q12: =IF($P12="","",$C12&"|"&$P12) | S12: =IF($A12="","",IFERROR(VALUE(TRIM(LEFT($R12,FIND("x",LOWER($R12))-1)))*VALUE(TRIM(MID($R12,FIND("x",LOWER($R12))+1,20))),0)) | T12: =IF(OR($A12="",$D12<>"Activo"),"",SUMPRODUCT(($D$2:$D$201="Activo")*(($C$2:$C$201<$C12)+(($C$2:$C$201=$C12)*($S$2:$S$201<$S12))+(($C$2:$C$201=$C12)*($S$2:$S$201=$S12)*($B$2:$B$201<$B12))))+1) | U12: =IF($T12="","","TODAS|"&$T12) | V12: =IF($A12="","",IFERROR(IF(COUNTIF('Compras'!$B:$B,$A12)=0,"",MINIFS('Compras'!$A:$A,'Compras'!$B:$B,$A12)),"")) | W12: =IF(OR($A12="",$V12=""),"",TODAY()-$V12) | X12: =IF($A12="","",SUMIF('Ventas'!$D:$D,$A12,'Ventas'!$F:$F)) | Y12: =IF($A12="","",IF(AND($X12>=3,$W12<>"",$W12<=15),"🔥 Se vende rápido — REABASTECE",IF($K12="Agotado","🔴 Agotado — reabastece",IF($K12="Stock bajo","🟠 Stock bajo","✅ Ok"))))
F13: =IF($A13="","",IFERROR(SUMIF('Compras'!$B:$B,$A13,'Compras'!$F:$F)/SUMIF('Compras'!$B:$B,$A13,'Compras'!$D:$D),0)) | G13: =IF($A13="","",SUMIF('Compras'!$B:$B,$A13,'Compras'!$D:$D)+SUMIF('Traslados'!$H:$H,$A13&"|Casa",'Traslados'!$D:$D)-SUMIF('Traslados'!$G:$G,$A13&"|Casa",'Traslados'!$D:$D)-SUMIF('Ventas'!$M:$M,$A13&"|Casa",'Ventas'!$F:$F)+SUMIF('Ajustes'!$H:$H,$A13&"|Casa",'Ajustes'!$D:$D)) | H13: =IF($A13="","",SUMIF('Traslados'!$H:$H,$A13&"|Mercado Libre",'Traslados'!$D:$D)-SUMIF('Traslados'!$G:$G,$A13&"|Mercado Libre",'Traslados'!$D:$D)-SUMIF('Ventas'!$M:$M,$A13&"|Mercado Libre",'Ventas'!$F:$F)+SUMIF('Ajustes'!$H:$H,$A13&"|Mercado Libre",'Ajustes'!$D:$D)) | I13: =IF($A13="","",$G13+$H13) | J13: =IF($A13="","",$I13*$F13) | K13: =IF($A13="","",IF($I13<=0,"Agotado",IF($I13<=$E13,"Stock bajo","Disponible"))) | L13: =IF($A13="","",IFERROR(VLOOKUP($C13,'Config'!$D$2:$E$30,2,FALSE),0)) | P13: =IF(OR($A13="",$D13<>"Activo"),"",SUMPRODUCT(($C$2:$C$201=$C13)*($D$2:$D$201="Activo")*(($S$2:$S$201<$S13)+(($S$2:$S$201=$S13)*($B$2:$B$201<$B13))))+1) | Q13: =IF($P13="","",$C13&"|"&$P13) | S13: =IF($A13="","",IFERROR(VALUE(TRIM(LEFT($R13,FIND("x",LOWER($R13))-1)))*VALUE(TRIM(MID($R13,FIND("x",LOWER($R13))+1,20))),0)) | T13: =IF(OR($A13="",$D13<>"Activo"),"",SUMPRODUCT(($D$2:$D$201="Activo")*(($C$2:$C$201<$C13)+(($C$2:$C$201=$C13)*($S$2:$S$201<$S13))+(($C$2:$C$201=$C13)*($S$2:$S$201=$S13)*($B$2:$B$201<$B13))))+1) | U13: =IF($T13="","","TODAS|"&$T13) | V13: =IF($A13="","",IFERROR(IF(COUNTIF('Compras'!$B:$B,$A13)=0,"",MINIFS('Compras'!$A:$A,'Compras'!$B:$B,$A13)),"")) | W13: =IF(OR($A13="",$V13=""),"",TODAY()-$V13) | X13: =IF($A13="","",SUMIF('Ventas'!$D:$D,$A13,'Ventas'!$F:$F)) | Y13: =IF($A13="","",IF(AND($X13>=3,$W13<>"",$W13<=15),"🔥 Se vende rápido — REABASTECE",IF($K13="Agotado","🔴 Agotado — reabastece",IF($K13="Stock bajo","🟠 Stock bajo","✅ Ok"))))
... F201: =IF($A201="","",IFERROR(SUMIF('Compras'!$B:$B,$A201,'Compras'!$F:$F)/SUMIF('Compras'!$B:$B,$A201,'Compras'!$D:$D),0)) | G201: =IF($A201="","",SUMIF('Compras'!$B:$B,$A201,'Compras'!$D:$D)+SUMIF('Traslados'!$H:$H,$A201&"|Casa",'Traslados'!$D:$D)-SUMIF('Traslados'!$G:$G,$A201&"|Casa",'Traslados'!$D:$D)-SUMIF('Ventas'!$M:$M,$A201&"|Casa",'Ventas'!$F:$F)+SUMIF('Ajustes'!$H:$H,$A201&"|Casa",'Ajustes'!$D:$D)) | H201: =IF($A201="","",SUMIF('Traslados'!$H:$H,$A201&"|Mercado Libre",'Traslados'!$D:$D)-SUMIF('Traslados'!$G:$G,$A201&"|Mercado Libre",'Traslados'!$D:$D)-SUMIF('Ventas'!$M:$M,$A201&"|Mercado Libre",'Ventas'!$F:$F)+SUMIF('Ajustes'!$H:$H,$A201&"|Mercado Libre",'Ajustes'!$D:$D)) | I201: =IF($A201="","",$G201+$H201) | J201: =IF($A201="","",$I201*$F201) | K201: =IF($A201="","",IF($I201<=0,"Agotado",IF($I201<=$E201,"Stock bajo","Disponible"))) | L201: =IF($A201="","",IFERROR(VLOOKUP($C201,'Config'!$D$2:$E$30,2,FALSE),0)) | P201: =IF(OR($A201="",$D201<>"Activo"),"",SUMPRODUCT(($C$2:$C$201=$C201)*($D$2:$D$201="Activo")*(($S$2:$S$201<$S201)+(($S$2:$S$201=$S201)*($B$2:$B$201<$B201))))+1) | Q201: =IF($P201="","",$C201&"|"&$P201) | S201: =IF($A201="","",IFERROR(VALUE(TRIM(LEFT($R201,FIND("x",LOWER($R201))-1)))*VALUE(TRIM(MID($R201,FIND("x",LOWER($R201))+1,20))),0)) | T201: =IF(OR($A201="",$D201<>"Activo"),"",SUMPRODUCT(($D$2:$D$201="Activo")*(($C$2:$C$201<$C201)+(($C$2:$C$201=$C201)*($S$2:$S$201<$S201))+(($C$2:$C$201=$C201)*($S$2:$S$201=$S201)*($B$2:$B$201<$B201))))+1) | U201: =IF($T201="","","TODAS|"&$T201) | V201: =IF($A201="","",IFERROR(IF(COUNTIF('Compras'!$B:$B,$A201)=0,"",MINIFS('Compras'!$A:$A,'Compras'!$B:$B,$A201)),"")) | W201: =IF(OR($A201="",$V201=""),"",TODAY()-$V201) | X201: =IF($A201="","",SUMIF('Ventas'!$D:$D,$A201,'Ventas'!$F:$F)) | Y201: =IF($A201="","",IF(AND($X201>=3,$W201<>"",$W201<=15),"🔥 Se vende rápido — REABASTECE",IF($K201="Agotado","🔴 Agotado — reabastece",IF($K201="Stock bajo","🟠 Stock bajo","✅ Ok"))))

Sheet Compras
A1: Fecha | B1: Código | C1: Producto | D1: Cantidad | E1: Costo Unitario | F1: Costo Total | G1: Medio de Pago | H1: ¿A crédito? | I1: Fecha Cierre | J1: Fecha Límite Pago | K1: Abonado | L1: Saldo | M1: Estado Pago | N1: Alerta Pago | O1: Fecha Llegada | P1: Días en Llegar
C2: =IF($B2="","",IFERROR(VLOOKUP($B2,'Catálogo'!$A:$B,2,FALSE),"⚠ Código no existe")) | F2: =IF($B2="","",$D2*$E2) | I2: =IF(OR($B2="",$H2<>"Sí"),"",IF(DAY($A2)<='Config'!$B$13,DATE(YEAR($A2),MONTH($A2),'Config'!$B$13),EOMONTH($A2,0)+'Config'!$B$13)) | J2: =IF($I2="","",DATE(YEAR(EOMONTH($I2,0)+1),MONTH(EOMONTH($I2,0)+1),'Config'!$B$14)) | L2: =IF($B2="","",MAX($F2-$K2,0)) | M2: =IF($B2="","",IF($H2<>"Sí","Pagado (contado)",IF($L2<=0,"Pagado",IF($K2>0,"Abono parcial","Pendiente")))) | N2: =IF(OR($B2="",$H2<>"Sí",$L2<=0),"",IF(TODAY()>$J2,"🔴 VENCIDO hace "&(TODAY()-$J2)&" día(s)",IF($J2-TODAY()<='Config'!$B$15,"🟠 Faltan "&($J2-TODAY())&" día(s) para pagar","🟢 Al día (paga el "&TEXT($J2,"dd/mm")&")"))) | P2: =IF(OR($B2="",$O2=""),"",$O2-$A2)
C3: =IF($B3="","",IFERROR(VLOOKUP($B3,'Catálogo'!$A:$B,2,FALSE),"⚠ Código no existe")) | F3: =IF($B3="","",$D3*$E3) | I3: =IF(OR($B3="",$H3<>"Sí"),"",IF(DAY($A3)<='Config'!$B$13,DATE(YEAR($A3),MONTH($A3),'Config'!$B$13),EOMONTH($A3,0)+'Config'!$B$13)) | J3: =IF($I3="","",DATE(YEAR(EOMONTH($I3,0)+1),MONTH(EOMONTH($I3,0)+1),'Config'!$B$14)) | L3: =IF($B3="","",MAX($F3-$K3,0)) | M3: =IF($B3="","",IF($H3<>"Sí","Pagado (contado)",IF($L3<=0,"Pagado",IF($K3>0,"Abono parcial","Pendiente")))) | N3: =IF(OR($B3="",$H3<>"Sí",$L3<=0),"",IF(TODAY()>$J3,"🔴 VENCIDO hace "&(TODAY()-$J3)&" día(s)",IF($J3-TODAY()<='Config'!$B$15,"🟠 Faltan "&($J3-TODAY())&" día(s) para pagar","🟢 Al día (paga el "&TEXT($J3,"dd/mm")&")"))) | P3: =IF(OR($B3="",$O3=""),"",$O3-$A3)
C4: =IF($B4="","",IFERROR(VLOOKUP($B4,'Catálogo'!$A:$B,2,FALSE),"⚠ Código no existe")) | F4: =IF($B4="","",$D4*$E4) | I4: =IF(OR($B4="",$H4<>"Sí"),"",IF(DAY($A4)<='Config'!$B$13,DATE(YEAR($A4),MONTH($A4),'Config'!$B$13),EOMONTH($A4,0)+'Config'!$B$13)) | J4: =IF($I4="","",DATE(YEAR(EOMONTH($I4,0)+1),MONTH(EOMONTH($I4,0)+1),'Config'!$B$14)) | L4: =IF($B4="","",MAX($F4-$K4,0)) | M4: =IF($B4="","",IF($H4<>"Sí","Pagado (contado)",IF($L4<=0,"Pagado",IF($K4>0,"Abono parcial","Pendiente")))) | N4: =IF(OR($B4="",$H4<>"Sí",$L4<=0),"",IF(TODAY()>$J4,"🔴 VENCIDO hace "&(TODAY()-$J4)&" día(s)",IF($J4-TODAY()<='Config'!$B$15,"🟠 Faltan "&($J4-TODAY())&" día(s) para pagar","🟢 Al día (paga el "&TEXT($J4,"dd/mm")&")"))) | P4: =IF(OR($B4="",$O4=""),"",$O4-$A4)
C5: =IF($B5="","",IFERROR(VLOOKUP($B5,'Catálogo'!$A:$B,2,FALSE),"⚠ Código no existe")) | F5: =IF($B5="","",$D5*$E5) | I5: =IF(OR($B5="",$H5<>"Sí"),"",IF(DAY($A5)<='Config'!$B$13,DATE(YEAR($A5),MONTH($A5),'Config'!$B$13),EOMONTH($A5,0)+'Config'!$B$13)) | J5: =IF($I5="","",DATE(YEAR(EOMONTH($I5,0)+1),MONTH(EOMONTH($I5,0)+1),'Config'!$B$14)) | L5: =IF($B5="","",MAX($F5-$K5,0)) | M5: =IF($B5="","",IF($H5<>"Sí","Pagado (contado)",IF($L5<=0,"Pagado",IF($K5>0,"Abono parcial","Pendiente")))) | N5: =IF(OR($B5="",$H5<>"Sí",$L5<=0),"",IF(TODAY()>$J5,"🔴 VENCIDO hace "&(TODAY()-$J5)&" día(s)",IF($J5-TODAY()<='Config'!$B$15,"🟠 Faltan "&($J5-TODAY())&" día(s) para pagar","🟢 Al día (paga el "&TEXT($J5,"dd/mm")&")"))) | P5: =IF(OR($B5="",$O5=""),"",$O5-$A5)
C6: =IF($B6="","",IFERROR(VLOOKUP($B6,'Catálogo'!$A:$B,2,FALSE),"⚠ Código no existe")) | F6: =IF($B6="","",$D6*$E6) | I6: =IF(OR($B6="",$H6<>"Sí"),"",IF(DAY($A6)<='Config'!$B$13,DATE(YEAR($A6),MONTH($A6),'Config'!$B$13),EOMONTH($A6,0)+'Config'!$B$13)) | J6: =IF($I6="","",DATE(YEAR(EOMONTH($I6,0)+1),MONTH(EOMONTH($I6,0)+1),'Config'!$B$14)) | L6: =IF($B6="","",MAX($F6-$K6,0)) | M6: =IF($B6="","",IF($H6<>"Sí","Pagado (contado)",IF($L6<=0,"Pagado",IF($K6>0,"Abono parcial","Pendiente")))) | N6: =IF(OR($B6="",$H6<>"Sí",$L6<=0),"",IF(TODAY()>$J6,"🔴 VENCIDO hace "&(TODAY()-$J6)&" día(s)",IF($J6-TODAY()<='Config'!$B$15,"🟠 Faltan "&($J6-TODAY())&" día(s) para pagar","🟢 Al día (paga el "&TEXT($J6,"dd/mm")&")"))) | P6: =IF(OR($B6="",$O6=""),"",$O6-$A6)
C7: =IF($B7="","",IFERROR(VLOOKUP($B7,'Catálogo'!$A:$B,2,FALSE),"⚠ Código no existe")) | F7: =IF($B7="","",$D7*$E7) | I7: =IF(OR($B7="",$H7<>"Sí"),"",IF(DAY($A7)<='Config'!$B$13,DATE(YEAR($A7),MONTH($A7),'Config'!$B$13),EOMONTH($A7,0)+'Config'!$B$13)) | J7: =IF($I7="","",DATE(YEAR(EOMONTH($I7,0)+1),MONTH(EOMONTH($I7,0)+1),'Config'!$B$14)) | L7: =IF($B7="","",MAX($F7-$K7,0)) | M7: =IF($B7="","",IF($H7<>"Sí","Pagado (contado)",IF($L7<=0,"Pagado",IF($K7>0,"Abono parcial","Pendiente")))) | N7: =IF(OR($B7="",$H7<>"Sí",$L7<=0),"",IF(TODAY()>$J7,"🔴 VENCIDO hace "&(TODAY()-$J7)&" día(s)",IF($J7-TODAY()<='Config'!$B$15,"🟠 Faltan "&($J7-TODAY())&" día(s) para pagar","🟢 Al día (paga el "&TEXT($J7,"dd/mm")&")"))) | P7: =IF(OR($B7="",$O7=""),"",$O7-$A7)
C8: =IF($B8="","",IFERROR(VLOOKUP($B8,'Catálogo'!$A:$B,2,FALSE),"⚠ Código no existe")) | F8: =IF($B8="","",$D8*$E8) | I8: =IF(OR($B8="",$H8<>"Sí"),"",IF(DAY($A8)<='Config'!$B$13,DATE(YEAR($A8),MONTH($A8),'Config'!$B$13),EOMONTH($A8,0)+'Config'!$B$13)) | J8: =IF($I8="","",DATE(YEAR(EOMONTH($I8,0)+1),MONTH(EOMONTH($I8,0)+1),'Config'!$B$14)) | L8: =IF($B8="","",MAX($F8-$K8,0)) | M8: =IF($B8="","",IF($H8<>"Sí","Pagado (contado)",IF($L8<=0,"Pagado",IF($K8>0,"Abono parcial","Pendiente")))) | N8: =IF(OR($B8="",$H8<>"Sí",$L8<=0),"",IF(TODAY()>$J8,"🔴 VENCIDO hace "&(TODAY()-$J8)&" día(s)",IF($J8-TODAY()<='Config'!$B$15,"🟠 Faltan "&($J8-TODAY())&" día(s) para pagar","🟢 Al día (paga el "&TEXT($J8,"dd/mm")&")"))) | P8: =IF(OR($B8="",$O8=""),"",$O8-$A8)
C9: =IF($B9="","",IFERROR(VLOOKUP($B9,'Catálogo'!$A:$B,2,FALSE),"⚠ Código no existe")) | F9: =IF($B9="","",$D9*$E9) | I9: =IF(OR($B9="",$H9<>"Sí"),"",IF(DAY($A9)<='Config'!$B$13,DATE(YEAR($A9),MONTH($A9),'Config'!$B$13),EOMONTH($A9,0)+'Config'!$B$13)) | J9: =IF($I9="","",DATE(YEAR(EOMONTH($I9,0)+1),MONTH(EOMONTH($I9,0)+1),'Config'!$B$14)) | L9: =IF($B9="","",MAX($F9-$K9,0)) | M9: =IF($B9="","",IF($H9<>"Sí","Pagado (contado)",IF($L9<=0,"Pagado",IF($K9>0,"Abono parcial","Pendiente")))) | N9: =IF(OR($B9="",$H9<>"Sí",$L9<=0),"",IF(TODAY()>$J9,"🔴 VENCIDO hace "&(TODAY()-$J9)&" día(s)",IF($J9-TODAY()<='Config'!$B$15,"🟠 Faltan "&($J9-TODAY())&" día(s) para pagar","🟢 Al día (paga el "&TEXT($J9,"dd/mm")&")"))) | P9: =IF(OR($B9="",$O9=""),"",$O9-$A9)
C10: =IF($B10="","",IFERROR(VLOOKUP($B10,'Catálogo'!$A:$B,2,FALSE),"⚠ Código no existe")) | F10: =IF($B10="","",$D10*$E10) | I10: =IF(OR($B10="",$H10<>"Sí"),"",IF(DAY($A10)<='Config'!$B$13,DATE(YEAR($A10),MONTH($A10),'Config'!$B$13),EOMONTH($A10,0)+'Config'!$B$13)) | J10: =IF($I10="","",DATE(YEAR(EOMONTH($I10,0)+1),MONTH(EOMONTH($I10,0)+1),'Config'!$B$14)) | L10: =IF($B10="","",MAX($F10-$K10,0)) | M10: =IF($B10="","",IF($H10<>"Sí","Pagado (contado)",IF($L10<=0,"Pagado",IF($K10>0,"Abono parcial","Pendiente")))) | N10: =IF(OR($B10="",$H10<>"Sí",$L10<=0),"",IF(TODAY()>$J10,"🔴 VENCIDO hace "&(TODAY()-$J10)&" día(s)",IF($J10-TODAY()<='Config'!$B$15,"🟠 Faltan "&($J10-TODAY())&" día(s) para pagar","🟢 Al día (paga el "&TEXT($J10,"dd/mm")&")"))) | P10: =IF(OR($B10="",$O10=""),"",$O10-$A10)
C11: =IF($B11="","",IFERROR(VLOOKUP($B11,'Catálogo'!$A:$B,2,FALSE),"⚠ Código no existe")) | F11: =IF($B11="","",$D11*$E11) | I11: =IF(OR($B11="",$H11<>"Sí"),"",IF(DAY($A11)<='Config'!$B$13,DATE(YEAR($A11),MONTH($A11),'Config'!$B$13),EOMONTH($A11,0)+'Config'!$B$13)) | J11: =IF($I11="","",DATE(YEAR(EOMONTH($I11,0)+1),MONTH(EOMONTH($I11,0)+1),'Config'!$B$14)) | L11: =IF($B11="","",MAX($F11-$K11,0)) | M11: =IF($B11="","",IF($H11<>"Sí","Pagado (contado)",IF($L11<=0,"Pagado",IF($K11>0,"Abono parcial","Pendiente")))) | N11: =IF(OR($B11="",$H11<>"Sí",$L11<=0),"",IF(TODAY()>$J11,"🔴 VENCIDO hace "&(TODAY()-$J11)&" día(s)",IF($J11-TODAY()<='Config'!$B$15,"🟠 Faltan "&($J11-TODAY())&" día(s) para pagar","🟢 Al día (paga el "&TEXT($J11,"dd/mm")&")"))) | P11: =IF(OR($B11="",$O11=""),"",$O11-$A11)
C12: =IF($B12="","",IFERROR(VLOOKUP($B12,'Catálogo'!$A:$B,2,FALSE),"⚠ Código no existe")) | F12: =IF($B12="","",$D12*$E12) | I12: =IF(OR($B12="",$H12<>"Sí"),"",IF(DAY($A12)<='Config'!$B$13,DATE(YEAR($A12),MONTH($A12),'Config'!$B$13),EOMONTH($A12,0)+'Config'!$B$13)) | J12: =IF($I12="","",DATE(YEAR(EOMONTH($I12,0)+1),MONTH(EOMONTH($I12,0)+1),'Config'!$B$14)) | L12: =IF($B12="","",MAX($F12-$K12,0)) | M12: =IF($B12="","",IF($H12<>"Sí","Pagado (contado)",IF($L12<=0,"Pagado",IF($K12>0,"Abono parcial","Pendiente")))) | N12: =IF(OR($B12="",$H12<>"Sí",$L12<=0),"",IF(TODAY()>$J12,"🔴 VENCIDO hace "&(TODAY()-$J12)&" día(s)",IF($J12-TODAY()<='Config'!$B$15,"🟠 Faltan "&($J12-TODAY())&" día(s) para pagar","🟢 Al día (paga el "&TEXT($J12,"dd/mm")&")"))) | P12: =IF(OR($B12="",$O12=""),"",$O12-$A12)
C13: =IF($B13="","",IFERROR(VLOOKUP($B13,'Catálogo'!$A:$B,2,FALSE),"⚠ Código no existe")) | F13: =IF($B13="","",$D13*$E13) | I13: =IF(OR($B13="",$H13<>"Sí"),"",IF(DAY($A13)<='Config'!$B$13,DATE(YEAR($A13),MONTH($A13),'Config'!$B$13),EOMONTH($A13,0)+'Config'!$B$13)) | J13: =IF($I13="","",DATE(YEAR(EOMONTH($I13,0)+1),MONTH(EOMONTH($I13,0)+1),'Config'!$B$14)) | L13: =IF($B13="","",MAX($F13-$K13,0)) | M13: =IF($B13="","",IF($H13<>"Sí","Pagado (contado)",IF($L13<=0,"Pagado",IF($K13>0,"Abono parcial","Pendiente")))) | N13: =IF(OR($B13="",$H13<>"Sí",$L13<=0),"",IF(TODAY()>$J13,"🔴 VENCIDO hace "&(TODAY()-$J13)&" día(s)",IF($J13-TODAY()<='Config'!$B$15,"🟠 Faltan "&($J13-TODAY())&" día(s) para pagar","🟢 Al día (paga el "&TEXT($J13,"dd/mm")&")"))) | P13: =IF(OR($B13="",$O13=""),"",$O13-$A13)
... C301: =IF($B301="","",IFERROR(VLOOKUP($B301,'Catálogo'!$A:$B,2,FALSE),"⚠ Código no existe")) | F301: =IF($B301="","",$D301*$E301) | I301: =IF(OR($B301="",$H301<>"Sí"),"",IF(DAY($A301)<='Config'!$B$13,DATE(YEAR($A301),MONTH($A301),'Config'!$B$13),EOMONTH($A301,0)+'Config'!$B$13)) | J301: =IF($I301="","",DATE(YEAR(EOMONTH($I301,0)+1),MONTH(EOMONTH($I301,0)+1),'Config'!$B$14)) | L301: =IF($B301="","",MAX($F301-$K301,0)) | M301: =IF($B301="","",IF($H301<>"Sí","Pagado (contado)",IF($L301<=0,"Pagado",IF($K301>0,"Abono parcial","Pendiente")))) | N301: =IF(OR($B301="",$H301<>"Sí",$L301<=0),"",IF(TODAY()>$J301,"🔴 VENCIDO hace "&(TODAY()-$J301)&" día(s)",IF($J301-TODAY()<='Config'!$B$15,"🟠 Faltan "&($J301-TODAY())&" día(s) para pagar","🟢 Al día (paga el "&TEXT($J301,"dd/mm")&")"))) | P301: =IF(OR($B301="",$O301=""),"",$O301-$A301)

Sheet Ventas
A1: Fecha | B1: N° Factura | C1: Cliente | D1: Código | E1: Producto | F1: Cantidad | G1: Ubicación | H1: Valor Recibido | I1: Costo Prom. Unit. | J1: Costo Total | K1: Costos Fijos | L1: Utilidad Neta | M1: clave | N1: Margen % | O1: Forma de Cobro
E2: =IF($D2="","",IFERROR(VLOOKUP($D2,'Catálogo'!$A:$B,2,FALSE),"⚠ Código no existe")) | I2: =IF($D2="","",IFERROR(VLOOKUP($D2,'Catálogo'!$A:$F,6,FALSE),0)) | J2: =IF($D2="","",$F2*$I2) | K2: =IF($D2="","",'Config'!$B$11+'Config'!$B$12) | L2: =IF($D2="","",$H2-$J2-$K2) | M2: =IF($D2="","",$D2&"|"&$G2) | N2: =IF($D2="","",IF($H2=0,0,$L2/$H2))
E3: =IF($D3="","",IFERROR(VLOOKUP($D3,'Catálogo'!$A:$B,2,FALSE),"⚠ Código no existe")) | I3: =IF($D3="","",IFERROR(VLOOKUP($D3,'Catálogo'!$A:$F,6,FALSE),0)) | J3: =IF($D3="","",$F3*$I3) | K3: =IF($D3="","",'Config'!$B$11+'Config'!$B$12) | L3: =IF($D3="","",$H3-$J3-$K3) | M3: =IF($D3="","",$D3&"|"&$G3) | N3: =IF($D3="","",IF($H3=0,0,$L3/$H3))
E4: =IF($D4="","",IFERROR(VLOOKUP($D4,'Catálogo'!$A:$B,2,FALSE),"⚠ Código no existe")) | I4: =IF($D4="","",IFERROR(VLOOKUP($D4,'Catálogo'!$A:$F,6,FALSE),0)) | J4: =IF($D4="","",$F4*$I4) | K4: =IF($D4="","",'Config'!$B$11+'Config'!$B$12) | L4: =IF($D4="","",$H4-$J4-$K4) | M4: =IF($D4="","",$D4&"|"&$G4) | N4: =IF($D4="","",IF($H4=0,0,$L4/$H4))
E5: =IF($D5="","",IFERROR(VLOOKUP($D5,'Catálogo'!$A:$B,2,FALSE),"⚠ Código no existe")) | I5: =IF($D5="","",IFERROR(VLOOKUP($D5,'Catálogo'!$A:$F,6,FALSE),0)) | J5: =IF($D5="","",$F5*$I5) | K5: =IF($D5="","",'Config'!$B$11+'Config'!$B$12) | L5: =IF($D5="","",$H5-$J5-$K5) | M5: =IF($D5="","",$D5&"|"&$G5) | N5: =IF($D5="","",IF($H5=0,0,$L5/$H5))
E6: =IF($D6="","",IFERROR(VLOOKUP($D6,'Catálogo'!$A:$B,2,FALSE),"⚠ Código no existe")) | I6: =IF($D6="","",IFERROR(VLOOKUP($D6,'Catálogo'!$A:$F,6,FALSE),0)) | J6: =IF($D6="","",$F6*$I6) | K6: =IF($D6="","",'Config'!$B$11+'Config'!$B$12) | L6: =IF($D6="","",$H6-$J6-$K6) | M6: =IF($D6="","",$D6&"|"&$G6) | N6: =IF($D6="","",IF($H6=0,0,$L6/$H6))
E7: =IF($D7="","",IFERROR(VLOOKUP($D7,'Catálogo'!$A:$B,2,FALSE),"⚠ Código no existe")) | I7: =IF($D7="","",IFERROR(VLOOKUP($D7,'Catálogo'!$A:$F,6,FALSE),0)) | J7: =IF($D7="","",$F7*$I7) | K7: =IF($D7="","",'Config'!$B$11+'Config'!$B$12) | L7: =IF($D7="","",$H7-$J7-$K7) | M7: =IF($D7="","",$D7&"|"&$G7) | N7: =IF($D7="","",IF($H7=0,0,$L7/$H7))
E8: =IF($D8="","",IFERROR(VLOOKUP($D8,'Catálogo'!$A:$B,2,FALSE),"⚠ Código no existe")) | I8: =IF($D8="","",IFERROR(VLOOKUP($D8,'Catálogo'!$A:$F,6,FALSE),0)) | J8: =IF($D8="","",$F8*$I8) | K8: =IF($D8="","",'Config'!$B$11+'Config'!$B$12) | L8: =IF($D8="","",$H8-$J8-$K8) | M8: =IF($D8="","",$D8&"|"&$G8) | N8: =IF($D8="","",IF($H8=0,0,$L8/$H8))
E9: =IF($D9="","",IFERROR(VLOOKUP($D9,'Catálogo'!$A:$B,2,FALSE),"⚠ Código no existe")) | I9: =IF($D9="","",IFERROR(VLOOKUP($D9,'Catálogo'!$A:$F,6,FALSE),0)) | J9: =IF($D9="","",$F9*$I9) | K9: =IF($D9="","",'Config'!$B$11+'Config'!$B$12) | L9: =IF($D9="","",$H9-$J9-$K9) | M9: =IF($D9="","",$D9&"|"&$G9) | N9: =IF($D9="","",IF($H9=0,0,$L9/$H9))
E10: =IF($D10="","",IFERROR(VLOOKUP($D10,'Catálogo'!$A:$B,2,FALSE),"⚠ Código no existe")) | I10: =IF($D10="","",IFERROR(VLOOKUP($D10,'Catálogo'!$A:$F,6,FALSE),0)) | J10: =IF($D10="","",$F10*$I10) | K10: =IF($D10="","",'Config'!$B$11+'Config'!$B$12) | L10: =IF($D10="","",$H10-$J10-$K10) | M10: =IF($D10="","",$D10&"|"&$G10) | N10: =IF($D10="","",IF($H10=0,0,$L10/$H10))
E11: =IF($D11="","",IFERROR(VLOOKUP($D11,'Catálogo'!$A:$B,2,FALSE),"⚠ Código no existe")) | I11: =IF($D11="","",IFERROR(VLOOKUP($D11,'Catálogo'!$A:$F,6,FALSE),0)) | J11: =IF($D11="","",$F11*$I11) | K11: =IF($D11="","",'Config'!$B$11+'Config'!$B$12) | L11: =IF($D11="","",$H11-$J11-$K11) | M11: =IF($D11="","",$D11&"|"&$G11) | N11: =IF($D11="","",IF($H11=0,0,$L11/$H11))
E12: =IF($D12="","",IFERROR(VLOOKUP($D12,'Catálogo'!$A:$B,2,FALSE),"⚠ Código no existe")) | I12: =IF($D12="","",IFERROR(VLOOKUP($D12,'Catálogo'!$A:$F,6,FALSE),0)) | J12: =IF($D12="","",$F12*$I12) | K12: =IF($D12="","",'Config'!$B$11+'Config'!$B$12) | L12: =IF($D12="","",$H12-$J12-$K12) | M12: =IF($D12="","",$D12&"|"&$G12) | N12: =IF($D12="","",IF($H12=0,0,$L12/$H12))
E13: =IF($D13="","",IFERROR(VLOOKUP($D13,'Catálogo'!$A:$B,2,FALSE),"⚠ Código no existe")) | I13: =IF($D13="","",IFERROR(VLOOKUP($D13,'Catálogo'!$A:$F,6,FALSE),0)) | J13: =IF($D13="","",$F13*$I13) | K13: =IF($D13="","",'Config'!$B$11+'Config'!$B$12) | L13: =IF($D13="","",$H13-$J13-$K13) | M13: =IF($D13="","",$D13&"|"&$G13) | N13: =IF($D13="","",IF($H13=0,0,$L13/$H13))
... E301: =IF($D301="","",IFERROR(VLOOKUP($D301,'Catálogo'!$A:$B,2,FALSE),"⚠ Código no existe")) | I301: =IF($D301="","",IFERROR(VLOOKUP($D301,'Catálogo'!$A:$F,6,FALSE),0)) | J301: =IF($D301="","",$F301*$I301) | K301: =IF($D301="","",'Config'!$B$11+'Config'!$B$12) | L301: =IF($D301="","",$H301-$J301-$K301) | M301: =IF($D301="","",$D301&"|"&$G301) | N301: =IF($D301="","",IF($H301=0,0,$L301/$H301))

Sheet Cierre Diario
A1: CIERRE DIARIO · CUADRE DE CAJA
A3: Fecha del cierre: | B3: =TODAY() | C3: ← cámbiala para ver otro día
A5: INGRESOS DEL DÍA (entran a tu caja / cuentas)
A6: Efectivo | B6: =SUMIFS('Ventas'!$H:$H,'Ventas'!$A:$A,$B$3,'Ventas'!$O:$O,"Efectivo")
A7: Nequi | B7: =SUMIFS('Ventas'!$H:$H,'Ventas'!$A:$A,$B$3,'Ventas'!$O:$O,"Nequi")
A8: Bancolombia | B8: =SUMIFS('Ventas'!$H:$H,'Ventas'!$A:$A,$B$3,'Ventas'!$O:$O,"Bancolombia")
A9: Bancolombia MM | B9: =SUMIFS('Ventas'!$H:$H,'Ventas'!$A:$A,$B$3,'Ventas'!$O:$O,"Bancolombia MM")
A10: Daviplata | B10: =SUMIFS('Ventas'!$H:$H,'Ventas'!$A:$A,$B$3,'Ventas'!$O:$O,"Daviplata")
A11: Davivienda | B11: =SUMIFS('Ventas'!$H:$H,'Ventas'!$A:$A,$B$3,'Ventas'!$O:$O,"Davivienda")
A12: Skydrops | B12: =SUMIFS('Ventas'!$H:$H,'Ventas'!$A:$A,$B$3,'Ventas'!$O:$O,"Skydrops")
A13: Subtotal ventas a caja (sin MELI) | B13: =SUM($B$6:$B$12)
A14: + Abonos de préstamos recibidos hoy | B14: =SUMIFS('Abonos Préstamos'!$C:$C,'Abonos Préstamos'!$A:$A,$B$3) | C14: Plata que te devolvieron hoy de un préstamo.
A15: = TOTAL INGRESOS A CAJA | B15: =$B$13+$B$14
A17: APARTE — Mercado Libre (NO entra a tu caja)
A18: Mercado Libre | B18: =SUMIFS('Ventas'!$H:$H,'Ventas'!$A:$A,$B$3,'Ventas'!$O:$O,"Mercado Libre") | C18: MELI te paga directo a tu cuenta; no se mezcla con la caja del día.
A20: SALIDAS DEL DÍA (sale de caja)
A21: Costos fijos por ventas (Mary + bolsa/etiqueta) | B21: =SUMIFS('Ventas'!$K:$K,'Ventas'!$A:$A,$B$3)
A22: Préstamos entregados hoy | B22: =SUMIFS('Préstamos'!$E:$E,'Préstamos'!$A:$A,$B$3) | C22: Plata que prestaste hoy (sale de la caja).
A23: Otro gasto 1 (escribe descripción →)
A24: Otro gasto 2
A25: Otro gasto 3
A26: = TOTAL SALIDAS DEL DÍA | B26: =$B$21+$B$22+SUM($B$23:$B$25)
A28: RESUMEN DEL DÍA
A29: Total ingresos a caja | B29: =$B$15
A30: Total salidas de caja | B30: =$B$26
A31: MOVIMIENTO NETO DE CAJA HOY | B31: =$B$15-$B$26
A32: Ganancia neta del día (solo ventas) | B32: =SUMIFS('Ventas'!$L:$L,'Ventas'!$A:$A,$B$3) | C32: Los préstamos NO son ganancia ni gasto: solo mueven la caja.
A33: Ventas por Mercado Libre (aparte) | B33: =$B$18
A35: CUADRE DE EFECTIVO (conteo físico de caja)
A36: Saldo inicial de caja (efectivo de ayer) →
A37: + Efectivo de ventas hoy | B37: =$B$6
A38: + Abonos recibidos en efectivo hoy (automático) | B38: =SUMIFS('Abonos Préstamos'!$C:$C,'Abonos Préstamos'!$A:$A,$B$3,'Abonos Préstamos'!$D:$D,"Efectivo") | C38: Sale solo de los abonos marcados como 'Efectivo'.
A39: − Salidas en efectivo (gastos / préstamos dados) →
A40: = EFECTIVO QUE DEBERÍA HABER | B40: =$B$36+$B$37+$B$38-$B$39
A41: Efectivo realmente contado en caja →
A42: DIFERENCIA (contado − esperado) | B42: =$B$41-$B$40 | C42: =IF($B$41="","Cuenta el efectivo y escríbelo arriba",IF(ROUND($B$42,0)=0,"✅ CUADRA",IF($B$42>0,"🔵 Sobra efectivo","🔴 Falta efectivo")))
A44: HISTORIAL — últimos 30 días
A45: Día | B45: Ventas a caja | C45: Ganancia neta
A46: =TODAY()-0 | B46: =SUMIFS('Ventas'!$H:$H,'Ventas'!$A:$A,$A46)-SUMIFS('Ventas'!$H:$H,'Ventas'!$A:$A,$A46,'Ventas'!$O:$O,"Mercado Libre") | C46: =SUMIFS('Ventas'!$L:$L,'Ventas'!$A:$A,$A46)
A47: =TODAY()-1 | B47: =SUMIFS('Ventas'!$H:$H,'Ventas'!$A:$A,$A47)-SUMIFS('Ventas'!$H:$H,'Ventas'!$A:$A,$A47,'Ventas'!$O:$O,"Mercado Libre") | C47: =SUMIFS('Ventas'!$L:$L,'Ventas'!$A:$A,$A47)
A48: =TODAY()-2 | B48: =SUMIFS('Ventas'!$H:$H,'Ventas'!$A:$A,$A48)-SUMIFS('Ventas'!$H:$H,'Ventas'!$A:$A,$A48,'Ventas'!$O:$O,"Mercado Libre") | C48: =SUMIFS('Ventas'!$L:$L,'Ventas'!$A:$A,$A48)
A49: =TODAY()-3 | B49: =SUMIFS('Ventas'!$H:$H,'Ventas'!$A:$A,$A49)-SUMIFS('Ventas'!$H:$H,'Ventas'!$A:$A,$A49,'Ventas'!$O:$O,"Mercado Libre") | C49: =SUMIFS('Ventas'!$L:$L,'Ventas'!$A:$A,$A49)
A50: =TODAY()-4 | B50: =SUMIFS('Ventas'!$H:$H,'Ventas'!$A:$A,$A50)-SUMIFS('Ventas'!$H:$H,'Ventas'!$A:$A,$A50,'Ventas'!$O:$O,"Mercado Libre") | C50: =SUMIFS('Ventas'!$L:$L,'Ventas'!$A:$A,$A50)
A51: =TODAY()-5 | B51: =SUMIFS('Ventas'!$H:$H,'Ventas'!$A:$A,$A51)-SUMIFS('Ventas'!$H:$H,'Ventas'!$A:$A,$A51,'Ventas'!$O:$O,"Mercado Libre") | C51: =SUMIFS('Ventas'!$L:$L,'Ventas'!$A:$A,$A51)
A52: =TODAY()-6 | B52: =SUMIFS('Ventas'!$H:$H,'Ventas'!$A:$A,$A52)-SUMIFS('Ventas'!$H:$H,'Ventas'!$A:$A,$A52,'Ventas'!$O:$O,"Mercado Libre") | C52: =SUMIFS('Ventas'!$L:$L,'Ventas'!$A:$A,$A52)
A53: =TODAY()-7 | B53: =SUMIFS('Ventas'!$H:$H,'Ventas'!$A:$A,$A53)-SUMIFS('Ventas'!$H:$H,'Ventas'!$A:$A,$A53,'Ventas'!$O:$O,"Mercado Libre") | C53: =SUMIFS('Ventas'!$L:$L,'Ventas'!$A:$A,$A53)
A54: =TODAY()-8 | B54: =SUMIFS('Ventas'!$H:$H,'Ventas'!$A:$A,$A54)-SUMIFS('Ventas'!$H:$H,'Ventas'!$A:$A,$A54,'Ventas'!$O:$O,"Mercado Libre") | C54: =SUMIFS('Ventas'!$L:$L,'Ventas'!$A:$A,$A54)
A55: =TODAY()-9 | B55: =SUMIFS('Ventas'!$H:$H,'Ventas'!$A:$A,$A55)-SUMIFS('Ventas'!$H:$H,'Ventas'!$A:$A,$A55,'Ventas'!$O:$O,"Mercado Libre") | C55: =SUMIFS('Ventas'!$L:$L,'Ventas'!$A:$A,$A55)
A56: =TODAY()-10 | B56: =SUMIFS('Ventas'!$H:$H,'Ventas'!$A:$A,$A56)-SUMIFS('Ventas'!$H:$H,'Ventas'!$A:$A,$A56,'Ventas'!$O:$O,"Mercado Libre") | C56: =SUMIFS('Ventas'!$L:$L,'Ventas'!$A:$A,$A56)
A57: =TODAY()-11 | B57: =SUMIFS('Ventas'!$H:$H,'Ventas'!$A:$A,$A57)-SUMIFS('Ventas'!$H:$H,'Ventas'!$A:$A,$A57,'Ventas'!$O:$O,"Mercado Libre") | C57: =SUMIFS('Ventas'!$L:$L,'Ventas'!$A:$A,$A57)
A58: =TODAY()-12 | B58: =SUMIFS('Ventas'!$H:$H,'Ventas'!$A:$A,$A58)-SUMIFS('Ventas'!$H:$H,'Ventas'!$A:$A,$A58,'Ventas'!$O:$O,"Mercado Libre") | C58: =SUMIFS('Ventas'!$L:$L,'Ventas'!$A:$A,$A58)
A59: =TODAY()-13 | B59: =SUMIFS('Ventas'!$H:$H,'Ventas'!$A:$A,$A59)-SUMIFS('Ventas'!$H:$H,'Ventas'!$A:$A,$A59,'Ventas'!$O:$O,"Mercado Libre") | C59: =SUMIFS('Ventas'!$L:$L,'Ventas'!$A:$A,$A59)
A60: =TODAY()-14 | B60: =SUMIFS('Ventas'!$H:$H,'Ventas'!$A:$A,$A60)-SUMIFS('Ventas'!$H:$H,'Ventas'!$A:$A,$A60,'Ventas'!$O:$O,"Mercado Libre") | C60: =SUMIFS('Ventas'!$L:$L,'Ventas'!$A:$A,$A60)
A61: =TODAY()-15 | B61: =SUMIFS('Ventas'!$H:$H,'Ventas'!$A:$A,$A61)-SUMIFS('Ventas'!$H:$H,'Ventas'!$A:$A,$A61,'Ventas'!$O:$O,"Mercado Libre") | C61: =SUMIFS('Ventas'!$L:$L,'Ventas'!$A:$A,$A61)
A62: =TODAY()-16 | B62: =SUMIFS('Ventas'!$H:$H,'Ventas'!$A:$A,$A62)-SUMIFS('Ventas'!$H:$H,'Ventas'!$A:$A,$A62,'Ventas'!$O:$O,"Mercado Libre") | C62: =SUMIFS('Ventas'!$L:$L,'Ventas'!$A:$A,$A62)
A63: =TODAY()-17 | B63: =SUMIFS('Ventas'!$H:$H,'Ventas'!$A:$A,$A63)-SUMIFS('Ventas'!$H:$H,'Ventas'!$A:$A,$A63,'Ventas'!$O:$O,"Mercado Libre") | C63: =SUMIFS('Ventas'!$L:$L,'Ventas'!$A:$A,$A63)
A64: =TODAY()-18 | B64: =SUMIFS('Ventas'!$H:$H,'Ventas'!$A:$A,$A64)-SUMIFS('Ventas'!$H:$H,'Ventas'!$A:$A,$A64,'Ventas'!$O:$O,"Mercado Libre") | C64: =SUMIFS('Ventas'!$L:$L,'Ventas'!$A:$A,$A64)
A65: =TODAY()-19 | B65: =SUMIFS('Ventas'!$H:$H,'Ventas'!$A:$A,$A65)-SUMIFS('Ventas'!$H:$H,'Ventas'!$A:$A,$A65,'Ventas'!$O:$O,"Mercado Libre") | C65: =SUMIFS('Ventas'!$L:$L,'Ventas'!$A:$A,$A65)
A66: =TODAY()-20 | B66: =SUMIFS('Ventas'!$H:$H,'Ventas'!$A:$A,$A66)-SUMIFS('Ventas'!$H:$H,'Ventas'!$A:$A,$A66,'Ventas'!$O:$O,"Mercado Libre") | C66: =SUMIFS('Ventas'!$L:$L,'Ventas'!$A:$A,$A66)
A67: =TODAY()-21 | B67: =SUMIFS('Ventas'!$H:$H,'Ventas'!$A:$A,$A67)-SUMIFS('Ventas'!$H:$H,'Ventas'!$A:$A,$A67,'Ventas'!$O:$O,"Mercado Libre") | C67: =SUMIFS('Ventas'!$L:$L,'Ventas'!$A:$A,$A67)
A68: =TODAY()-22 | B68: =SUMIFS('Ventas'!$H:$H,'Ventas'!$A:$A,$A68)-SUMIFS('Ventas'!$H:$H,'Ventas'!$A:$A,$A68,'Ventas'!$O:$O,"Mercado Libre") | C68: =SUMIFS('Ventas'!$L:$L,'Ventas'!$A:$A,$A68)
A69: =TODAY()-23 | B69: =SUMIFS('Ventas'!$H:$H,'Ventas'!$A:$A,$A69)-SUMIFS('Ventas'!$H:$H,'Ventas'!$A:$A,$A69,'Ventas'!$O:$O,"Mercado Libre") | C69: =SUMIFS('Ventas'!$L:$L,'Ventas'!$A:$A,$A69)
A70: =TODAY()-24 | B70: =SUMIFS('Ventas'!$H:$H,'Ventas'!$A:$A,$A70)-SUMIFS('Ventas'!$H:$H,'Ventas'!$A:$A,$A70,'Ventas'!$O:$O,"Mercado Libre") | C70: =SUMIFS('Ventas'!$L:$L,'Ventas'!$A:$A,$A70)
A71: =TODAY()-25 | B71: =SUMIFS('Ventas'!$H:$H,'Ventas'!$A:$A,$A71)-SUMIFS('Ventas'!$H:$H,'Ventas'!$A:$A,$A71,'Ventas'!$O:$O,"Mercado Libre") | C71: =SUMIFS('Ventas'!$L:$L,'Ventas'!$A:$A,$A71)
A72: =TODAY()-26 | B72: =SUMIFS('Ventas'!$H:$H,'Ventas'!$A:$A,$A72)-SUMIFS('Ventas'!$H:$H,'Ventas'!$A:$A,$A72,'Ventas'!$O:$O,"Mercado Libre") | C72: =SUMIFS('Ventas'!$L:$L,'Ventas'!$A:$A,$A72)
A73: =TODAY()-27 | B73: =SUMIFS('Ventas'!$H:$H,'Ventas'!$A:$A,$A73)-SUMIFS('Ventas'!$H:$H,'Ventas'!$A:$A,$A73,'Ventas'!$O:$O,"Mercado Libre") | C73: =SUMIFS('Ventas'!$L:$L,'Ventas'!$A:$A,$A73)
A74: =TODAY()-28 | B74: =SUMIFS('Ventas'!$H:$H,'Ventas'!$A:$A,$A74)-SUMIFS('Ventas'!$H:$H,'Ventas'!$A:$A,$A74,'Ventas'!$O:$O,"Mercado Libre") | C74: =SUMIFS('Ventas'!$L:$L,'Ventas'!$A:$A,$A74)
A75: =TODAY()-29 | B75: =SUMIFS('Ventas'!$H:$H,'Ventas'!$A:$A,$A75)-SUMIFS('Ventas'!$H:$H,'Ventas'!$A:$A,$A75,'Ventas'!$O:$O,"Mercado Libre") | C75: =SUMIFS('Ventas'!$L:$L,'Ventas'!$A:$A,$A75)

Sheet Billeteras
A1: SALDOS POR BILLETERA (en tiempo real)
A2: Billetera | B2: Saldo Inicial | C2: Saldo Actual | D2: Nota
A3: Efectivo | C3: =$B3+SUMIF('Ventas'!$O:$O,$A3,'Ventas'!$H:$H)+SUMIF('Abonos Préstamos'!$D:$D,$A3,'Abonos Préstamos'!$C:$C)+SUMIF('Movimientos'!$D:$D,$A3,'Movimientos'!$E:$E)-SUMIF('Movimientos'!$C:$C,$A3,'Movimientos'!$E:$E)-SUMIF('Préstamos'!$K:$K,$A3,'Préstamos'!$E:$E)-SUMIF('Pagos Tarjeta'!$D:$D,$A3,'Pagos Tarjeta'!$C:$C)-SUMIFS('Compras'!$F:$F,'Compras'!$H:$H,"No",'Compras'!$G:$G,$A3)
A4: Nequi | C4: =$B4+SUMIF('Ventas'!$O:$O,$A4,'Ventas'!$H:$H)+SUMIF('Abonos Préstamos'!$D:$D,$A4,'Abonos Préstamos'!$C:$C)+SUMIF('Movimientos'!$D:$D,$A4,'Movimientos'!$E:$E)-SUMIF('Movimientos'!$C:$C,$A4,'Movimientos'!$E:$E)-SUMIF('Préstamos'!$K:$K,$A4,'Préstamos'!$E:$E)-SUMIF('Pagos Tarjeta'!$D:$D,$A4,'Pagos Tarjeta'!$C:$C)-SUMIFS('Compras'!$F:$F,'Compras'!$H:$H,"No",'Compras'!$G:$G,$A4)
A5: Bancolombia | C5: =$B5+SUMIF('Ventas'!$O:$O,$A5,'Ventas'!$H:$H)+SUMIF('Abonos Préstamos'!$D:$D,$A5,'Abonos Préstamos'!$C:$C)+SUMIF('Movimientos'!$D:$D,$A5,'Movimientos'!$E:$E)-SUMIF('Movimientos'!$C:$C,$A5,'Movimientos'!$E:$E)-SUMIF('Préstamos'!$K:$K,$A5,'Préstamos'!$E:$E)-SUMIF('Pagos Tarjeta'!$D:$D,$A5,'Pagos Tarjeta'!$C:$C)-SUMIFS('Compras'!$F:$F,'Compras'!$H:$H,"No",'Compras'!$G:$G,$A5)
A6: Bancolombia MM | C6: =$B6+SUMIF('Ventas'!$O:$O,$A6,'Ventas'!$H:$H)+SUMIF('Abonos Préstamos'!$D:$D,$A6,'Abonos Préstamos'!$C:$C)+SUMIF('Movimientos'!$D:$D,$A6,'Movimientos'!$E:$E)-SUMIF('Movimientos'!$C:$C,$A6,'Movimientos'!$E:$E)-SUMIF('Préstamos'!$K:$K,$A6,'Préstamos'!$E:$E)-SUMIF('Pagos Tarjeta'!$D:$D,$A6,'Pagos Tarjeta'!$C:$C)-SUMIFS('Compras'!$F:$F,'Compras'!$H:$H,"No",'Compras'!$G:$G,$A6)
A7: Daviplata | C7: =$B7+SUMIF('Ventas'!$O:$O,$A7,'Ventas'!$H:$H)+SUMIF('Abonos Préstamos'!$D:$D,$A7,'Abonos Préstamos'!$C:$C)+SUMIF('Movimientos'!$D:$D,$A7,'Movimientos'!$E:$E)-SUMIF('Movimientos'!$C:$C,$A7,'Movimientos'!$E:$E)-SUMIF('Préstamos'!$K:$K,$A7,'Préstamos'!$E:$E)-SUMIF('Pagos Tarjeta'!$D:$D,$A7,'Pagos Tarjeta'!$C:$C)-SUMIFS('Compras'!$F:$F,'Compras'!$H:$H,"No",'Compras'!$G:$G,$A7)
A8: Davivienda | C8: =$B8+SUMIF('Ventas'!$O:$O,$A8,'Ventas'!$H:$H)+SUMIF('Abonos Préstamos'!$D:$D,$A8,'Abonos Préstamos'!$C:$C)+SUMIF('Movimientos'!$D:$D,$A8,'Movimientos'!$E:$E)-SUMIF('Movimientos'!$C:$C,$A8,'Movimientos'!$E:$E)-SUMIF('Préstamos'!$K:$K,$A8,'Préstamos'!$E:$E)-SUMIF('Pagos Tarjeta'!$D:$D,$A8,'Pagos Tarjeta'!$C:$C)-SUMIFS('Compras'!$F:$F,'Compras'!$H:$H,"No",'Compras'!$G:$G,$A8)
A9: Mercado Libre | C9: =$B9+SUMIF('Ventas'!$O:$O,$A9,'Ventas'!$H:$H)+SUMIF('Abonos Préstamos'!$D:$D,$A9,'Abonos Préstamos'!$C:$C)+SUMIF('Movimientos'!$D:$D,$A9,'Movimientos'!$E:$E)-SUMIF('Movimientos'!$C:$C,$A9,'Movimientos'!$E:$E)-SUMIF('Préstamos'!$K:$K,$A9,'Préstamos'!$E:$E)-SUMIF('Pagos Tarjeta'!$D:$D,$A9,'Pagos Tarjeta'!$C:$C)-SUMIFS('Compras'!$F:$F,'Compras'!$H:$H,"No",'Compras'!$G:$G,$A9) | D9: Por cobrar — retíralo a una billetera (hoja Movimientos)
A10: Skydrops | C10: =$B10+SUMIF('Ventas'!$O:$O,$A10,'Ventas'!$H:$H)+SUMIF('Abonos Préstamos'!$D:$D,$A10,'Abonos Préstamos'!$C:$C)+SUMIF('Movimientos'!$D:$D,$A10,'Movimientos'!$E:$E)-SUMIF('Movimientos'!$C:$C,$A10,'Movimientos'!$E:$E)-SUMIF('Préstamos'!$K:$K,$A10,'Préstamos'!$E:$E)-SUMIF('Pagos Tarjeta'!$D:$D,$A10,'Pagos Tarjeta'!$C:$C)-SUMIFS('Compras'!$F:$F,'Compras'!$H:$H,"No",'Compras'!$G:$G,$A10) | D10: Por cobrar — retíralo a una billetera (hoja Movimientos)
A11: TOTAL en billeteras | C11: =SUM($C$3:$C$10)
A13: Escribe el Saldo Inicial UNA vez (lo que tienes hoy). De ahí en adelante el Saldo Actual se mueve solo: ventas, abonos, transferencias, préstamos, pagos de tarjeta y compras de contado.

Sheet Tarjetas
A1: DEUDA POR TARJETA DE CRÉDITO
A2: Tarjeta | B2: Comprado a crédito | C2: Pagado | D2: Saldo (debes)
A3: TC Bancolombia 1 (1517) | B3: =SUMIFS('Compras'!$F:$F,'Compras'!$H:$H,"Sí",'Compras'!$G:$G,$A3) | C3: =SUMIF('Pagos Tarjeta'!$B:$B,$A3,'Pagos Tarjeta'!$C:$C) | D3: =MAX($B3-$C3,0)
A4: TC Bancolombia 2 (0554) | B4: =SUMIFS('Compras'!$F:$F,'Compras'!$H:$H,"Sí",'Compras'!$G:$G,$A4) | C4: =SUMIF('Pagos Tarjeta'!$B:$B,$A4,'Pagos Tarjeta'!$C:$C) | D4: =MAX($B4-$C4,0)
A5: TC Bancolombia 3 (4582) | B5: =SUMIFS('Compras'!$F:$F,'Compras'!$H:$H,"Sí",'Compras'!$G:$G,$A5) | C5: =SUMIF('Pagos Tarjeta'!$B:$B,$A5,'Pagos Tarjeta'!$C:$C) | D5: =MAX($B5-$C5,0)
A6: TC Bancolombia 4 (8366) | B6: =SUMIFS('Compras'!$F:$F,'Compras'!$H:$H,"Sí",'Compras'!$G:$G,$A6) | C6: =SUMIF('Pagos Tarjeta'!$B:$B,$A6,'Pagos Tarjeta'!$C:$C) | D6: =MAX($B6-$C6,0)
A7: TC Bancolombia 5 (0623) | B7: =SUMIFS('Compras'!$F:$F,'Compras'!$H:$H,"Sí",'Compras'!$G:$G,$A7) | C7: =SUMIF('Pagos Tarjeta'!$B:$B,$A7,'Pagos Tarjeta'!$C:$C) | D7: =MAX($B7-$C7,0)
A8: TC Bancolombia MM 6 (6423) | B8: =SUMIFS('Compras'!$F:$F,'Compras'!$H:$H,"Sí",'Compras'!$G:$G,$A8) | C8: =SUMIF('Pagos Tarjeta'!$B:$B,$A8,'Pagos Tarjeta'!$C:$C) | D8: =MAX($B8-$C8,0)
A9: TC Bancolombia MM 7 (2459) | B9: =SUMIFS('Compras'!$F:$F,'Compras'!$H:$H,"Sí",'Compras'!$G:$G,$A9) | C9: =SUMIF('Pagos Tarjeta'!$B:$B,$A9,'Pagos Tarjeta'!$C:$C) | D9: =MAX($B9-$C9,0)
A10: TC NU 8 (3750) | B10: =SUMIFS('Compras'!$F:$F,'Compras'!$H:$H,"Sí",'Compras'!$G:$G,$A10) | C10: =SUMIF('Pagos Tarjeta'!$B:$B,$A10,'Pagos Tarjeta'!$C:$C) | D10: =MAX($B10-$C10,0)
A11: TOTAL QUE DEBO EN TARJETAS | D11: =SUM($D$3:$D$10)
A13: Las compras a crédito (hoja Compras) suman; los abonos (hoja Pagos Tarjeta) restan.

Sheet Movimientos
A1: Fecha | B1: Tipo | C1: Billetera Origen | D1: Billetera Destino | E1: Valor | F1: Nota | H1: Origen = de dónde sale la plata · Destino = a dónde llega. Para un gasto, deja el Destino vacío.

Sheet Pagos Tarjeta
A1: Fecha | B1: Tarjeta | C1: Valor | D1: Billetera (de dónde salió) | E1: Nota

Sheet Traslados
A1: Fecha | B1: Código | C1: Producto | D1: Cantidad | E1: Origen | F1: Destino | G1: claveOrigen | H1: claveDestino
C2: =IF($B2="","",IFERROR(VLOOKUP($B2,'Catálogo'!$A:$B,2,FALSE),"⚠ Código no existe")) | G2: =IF($B2="","",$B2&"|"&$E2) | H2: =IF($B2="","",$B2&"|"&$F2)
C3: =IF($B3="","",IFERROR(VLOOKUP($B3,'Catálogo'!$A:$B,2,FALSE),"⚠ Código no existe")) | G3: =IF($B3="","",$B3&"|"&$E3) | H3: =IF($B3="","",$B3&"|"&$F3)
C4: =IF($B4="","",IFERROR(VLOOKUP($B4,'Catálogo'!$A:$B,2,FALSE),"⚠ Código no existe")) | G4: =IF($B4="","",$B4&"|"&$E4) | H4: =IF($B4="","",$B4&"|"&$F4)
C5: =IF($B5="","",IFERROR(VLOOKUP($B5,'Catálogo'!$A:$B,2,FALSE),"⚠ Código no existe")) | G5: =IF($B5="","",$B5&"|"&$E5) | H5: =IF($B5="","",$B5&"|"&$F5)
C6: =IF($B6="","",IFERROR(VLOOKUP($B6,'Catálogo'!$A:$B,2,FALSE),"⚠ Código no existe")) | G6: =IF($B6="","",$B6&"|"&$E6) | H6: =IF($B6="","",$B6&"|"&$F6)
C7: =IF($B7="","",IFERROR(VLOOKUP($B7,'Catálogo'!$A:$B,2,FALSE),"⚠ Código no existe")) | G7: =IF($B7="","",$B7&"|"&$E7) | H7: =IF($B7="","",$B7&"|"&$F7)
C8: =IF($B8="","",IFERROR(VLOOKUP($B8,'Catálogo'!$A:$B,2,FALSE),"⚠ Código no existe")) | G8: =IF($B8="","",$B8&"|"&$E8) | H8: =IF($B8="","",$B8&"|"&$F8)
C9: =IF($B9="","",IFERROR(VLOOKUP($B9,'Catálogo'!$A:$B,2,FALSE),"⚠ Código no existe")) | G9: =IF($B9="","",$B9&"|"&$E9) | H9: =IF($B9="","",$B9&"|"&$F9)
C10: =IF($B10="","",IFERROR(VLOOKUP($B10,'Catálogo'!$A:$B,2,FALSE),"⚠ Código no existe")) | G10: =IF($B10="","",$B10&"|"&$E10) | H10: =IF($B10="","",$B10&"|"&$F10)
C11: =IF($B11="","",IFERROR(VLOOKUP($B11,'Catálogo'!$A:$B,2,FALSE),"⚠ Código no existe")) | G11: =IF($B11="","",$B11&"|"&$E11) | H11: =IF($B11="","",$B11&"|"&$F11)
C12: =IF($B12="","",IFERROR(VLOOKUP($B12,'Catálogo'!$A:$B,2,FALSE),"⚠ Código no existe")) | G12: =IF($B12="","",$B12&"|"&$E12) | H12: =IF($B12="","",$B12&"|"&$F12)
C13: =IF($B13="","",IFERROR(VLOOKUP($B13,'Catálogo'!$A:$B,2,FALSE),"⚠ Código no existe")) | G13: =IF($B13="","",$B13&"|"&$E13) | H13: =IF($B13="","",$B13&"|"&$F13)
... C301: =IF($B301="","",IFERROR(VLOOKUP($B301,'Catálogo'!$A:$B,2,FALSE),"⚠ Código no existe")) | G301: =IF($B301="","",$B301&"|"&$E301) | H301: =IF($B301="","",$B301&"|"&$F301)

Sheet Ajustes
A1: Fecha | B1: Código | C1: Producto | D1: Cantidad (+/-) | E1: Ubicación | F1: Motivo | G1: Nota | H1: clave
C2: =IF($B2="","",IFERROR(VLOOKUP($B2,'Catálogo'!$A:$B,2,FALSE),"⚠ Código no existe")) | H2: =IF($B2="","",$B2&"|"&$E2)
C3: =IF($B3="","",IFERROR(VLOOKUP($B3,'Catálogo'!$A:$B,2,FALSE),"⚠ Código no existe")) | H3: =IF($B3="","",$B3&"|"&$E3)
C4: =IF($B4="","",IFERROR(VLOOKUP($B4,'Catálogo'!$A:$B,2,FALSE),"⚠ Código no existe")) | H4: =IF($B4="","",$B4&"|"&$E4)
C5: =IF($B5="","",IFERROR(VLOOKUP($B5,'Catálogo'!$A:$B,2,FALSE),"⚠ Código no existe")) | H5: =IF($B5="","",$B5&"|"&$E5)
C6: =IF($B6="","",IFERROR(VLOOKUP($B6,'Catálogo'!$A:$B,2,FALSE),"⚠ Código no existe")) | H6: =IF($B6="","",$B6&"|"&$E6)
C7: =IF($B7="","",IFERROR(VLOOKUP($B7,'Catálogo'!$A:$B,2,FALSE),"⚠ Código no existe")) | H7: =IF($B7="","",$B7&"|"&$E7)
C8: =IF($B8="","",IFERROR(VLOOKUP($B8,'Catálogo'!$A:$B,2,FALSE),"⚠ Código no existe")) | H8: =IF($B8="","",$B8&"|"&$E8)
C9: =IF($B9="","",IFERROR(VLOOKUP($B9,'Catálogo'!$A:$B,2,FALSE),"⚠ Código no existe")) | H9: =IF($B9="","",$B9&"|"&$E9)
C10: =IF($B10="","",IFERROR(VLOOKUP($B10,'Catálogo'!$A:$B,2,FALSE),"⚠ Código no existe")) | H10: =IF($B10="","",$B10&"|"&$E10)
C11: =IF($B11="","",IFERROR(VLOOKUP($B11,'Catálogo'!$A:$B,2,FALSE),"⚠ Código no existe")) | H11: =IF($B11="","",$B11&"|"&$E11)
C12: =IF($B12="","",IFERROR(VLOOKUP($B12,'Catálogo'!$A:$B,2,FALSE),"⚠ Código no existe")) | H12: =IF($B12="","",$B12&"|"&$E12)
C13: =IF($B13="","",IFERROR(VLOOKUP($B13,'Catálogo'!$A:$B,2,FALSE),"⚠ Código no existe")) | H13: =IF($B13="","",$B13&"|"&$E13)
... C301: =IF($B301="","",IFERROR(VLOOKUP($B301,'Catálogo'!$A:$B,2,FALSE),"⚠ Código no existe")) | H301: =IF($B301="","",$B301&"|"&$E301)

Sheet Préstamos
A1: Fecha | B1: Persona | C1: Teléfono | D1: Motivo / Nota | E1: Valor Prestado | F1: Abonado | G1: Saldo | H1: Estado | I1: Días sin pagar | J1: Alerta | K1: Billetera origen
F2: =IF($B2="","",SUMIF('Abonos Préstamos'!$B:$B,$B2,'Abonos Préstamos'!$C:$C)) | G2: =IF($B2="","",MAX($E2-$F2,0)) | H2: =IF($B2="","",IF($G2<=0,"Pagado",IF($F2>0,"Abono parcial","Pendiente"))) | I2: =IF(OR($B2="",$G2<=0),"",TODAY()-$A2) | J2: =IF($B2="","",IF($G2<=0,"✅ Pagado",IF($I2>30,"🔴 Cóbrale ya ("&$I2&" días)",IF($I2>15,"🟠 Lleva "&$I2&" días","🟢 Reciente ("&$I2&" días)"))))
F3: =IF($B3="","",SUMIF('Abonos Préstamos'!$B:$B,$B3,'Abonos Préstamos'!$C:$C)) | G3: =IF($B3="","",MAX($E3-$F3,0)) | H3: =IF($B3="","",IF($G3<=0,"Pagado",IF($F3>0,"Abono parcial","Pendiente"))) | I3: =IF(OR($B3="",$G3<=0),"",TODAY()-$A3) | J3: =IF($B3="","",IF($G3<=0,"✅ Pagado",IF($I3>30,"🔴 Cóbrale ya ("&$I3&" días)",IF($I3>15,"🟠 Lleva "&$I3&" días","🟢 Reciente ("&$I3&" días)"))))
F4: =IF($B4="","",SUMIF('Abonos Préstamos'!$B:$B,$B4,'Abonos Préstamos'!$C:$C)) | G4: =IF($B4="","",MAX($E4-$F4,0)) | H4: =IF($B4="","",IF($G4<=0,"Pagado",IF($F4>0,"Abono parcial","Pendiente"))) | I4: =IF(OR($B4="",$G4<=0),"",TODAY()-$A4) | J4: =IF($B4="","",IF($G4<=0,"✅ Pagado",IF($I4>30,"🔴 Cóbrale ya ("&$I4&" días)",IF($I4>15,"🟠 Lleva "&$I4&" días","🟢 Reciente ("&$I4&" días)"))))
F5: =IF($B5="","",SUMIF('Abonos Préstamos'!$B:$B,$B5,'Abonos Préstamos'!$C:$C)) | G5: =IF($B5="","",MAX($E5-$F5,0)) | H5: =IF($B5="","",IF($G5<=0,"Pagado",IF($F5>0,"Abono parcial","Pendiente"))) | I5: =IF(OR($B5="",$G5<=0),"",TODAY()-$A5) | J5: =IF($B5="","",IF($G5<=0,"✅ Pagado",IF($I5>30,"🔴 Cóbrale ya ("&$I5&" días)",IF($I5>15,"🟠 Lleva "&$I5&" días","🟢 Reciente ("&$I5&" días)"))))
F6: =IF($B6="","",SUMIF('Abonos Préstamos'!$B:$B,$B6,'Abonos Préstamos'!$C:$C)) | G6: =IF($B6="","",MAX($E6-$F6,0)) | H6: =IF($B6="","",IF($G6<=0,"Pagado",IF($F6>0,"Abono parcial","Pendiente"))) | I6: =IF(OR($B6="",$G6<=0),"",TODAY()-$A6) | J6: =IF($B6="","",IF($G6<=0,"✅ Pagado",IF($I6>30,"🔴 Cóbrale ya ("&$I6&" días)",IF($I6>15,"🟠 Lleva "&$I6&" días","🟢 Reciente ("&$I6&" días)"))))
F7: =IF($B7="","",SUMIF('Abonos Préstamos'!$B:$B,$B7,'Abonos Préstamos'!$C:$C)) | G7: =IF($B7="","",MAX($E7-$F7,0)) | H7: =IF($B7="","",IF($G7<=0,"Pagado",IF($F7>0,"Abono parcial","Pendiente"))) | I7: =IF(OR($B7="",$G7<=0),"",TODAY()-$A7) | J7: =IF($B7="","",IF($G7<=0,"✅ Pagado",IF($I7>30,"🔴 Cóbrale ya ("&$I7&" días)",IF($I7>15,"🟠 Lleva "&$I7&" días","🟢 Reciente ("&$I7&" días)"))))
F8: =IF($B8="","",SUMIF('Abonos Préstamos'!$B:$B,$B8,'Abonos Préstamos'!$C:$C)) | G8: =IF($B8="","",MAX($E8-$F8,0)) | H8: =IF($B8="","",IF($G8<=0,"Pagado",IF($F8>0,"Abono parcial","Pendiente"))) | I8: =IF(OR($B8="",$G8<=0),"",TODAY()-$A8) | J8: =IF($B8="","",IF($G8<=0,"✅ Pagado",IF($I8>30,"🔴 Cóbrale ya ("&$I8&" días)",IF($I8>15,"🟠 Lleva "&$I8&" días","🟢 Reciente ("&$I8&" días)"))))
F9: =IF($B9="","",SUMIF('Abonos Préstamos'!$B:$B,$B9,'Abonos Préstamos'!$C:$C)) | G9: =IF($B9="","",MAX($E9-$F9,0)) | H9: =IF($B9="","",IF($G9<=0,"Pagado",IF($F9>0,"Abono parcial","Pendiente"))) | I9: =IF(OR($B9="",$G9<=0),"",TODAY()-$A9) | J9: =IF($B9="","",IF($G9<=0,"✅ Pagado",IF($I9>30,"🔴 Cóbrale ya ("&$I9&" días)",IF($I9>15,"🟠 Lleva "&$I9&" días","🟢 Reciente ("&$I9&" días)"))))
F10: =IF($B10="","",SUMIF('Abonos Préstamos'!$B:$B,$B10,'Abonos Préstamos'!$C:$C)) | G10: =IF($B10="","",MAX($E10-$F10,0)) | H10: =IF($B10="","",IF($G10<=0,"Pagado",IF($F10>0,"Abono parcial","Pendiente"))) | I10: =IF(OR($B10="",$G10<=0),"",TODAY()-$A10) | J10: =IF($B10="","",IF($G10<=0,"✅ Pagado",IF($I10>30,"🔴 Cóbrale ya ("&$I10&" días)",IF($I10>15,"🟠 Lleva "&$I10&" días","🟢 Reciente ("&$I10&" días)"))))
F11: =IF($B11="","",SUMIF('Abonos Préstamos'!$B:$B,$B11,'Abonos Préstamos'!$C:$C)) | G11: =IF($B11="","",MAX($E11-$F11,0)) | H11: =IF($B11="","",IF($G11<=0,"Pagado",IF($F11>0,"Abono parcial","Pendiente"))) | I11: =IF(OR($B11="",$G11<=0),"",TODAY()-$A11) | J11: =IF($B11="","",IF($G11<=0,"✅ Pagado",IF($I11>30,"🔴 Cóbrale ya ("&$I11&" días)",IF($I11>15,"🟠 Lleva "&$I11&" días","🟢 Reciente ("&$I11&" días)"))))
F12: =IF($B12="","",SUMIF('Abonos Préstamos'!$B:$B,$B12,'Abonos Préstamos'!$C:$C)) | G12: =IF($B12="","",MAX($E12-$F12,0)) | H12: =IF($B12="","",IF($G12<=0,"Pagado",IF($F12>0,"Abono parcial","Pendiente"))) | I12: =IF(OR($B12="",$G12<=0),"",TODAY()-$A12) | J12: =IF($B12="","",IF($G12<=0,"✅ Pagado",IF($I12>30,"🔴 Cóbrale ya ("&$I12&" días)",IF($I12>15,"🟠 Lleva "&$I12&" días","🟢 Reciente ("&$I12&" días)"))))
F13: =IF($B13="","",SUMIF('Abonos Préstamos'!$B:$B,$B13,'Abonos Préstamos'!$C:$C)) | G13: =IF($B13="","",MAX($E13-$F13,0)) | H13: =IF($B13="","",IF($G13<=0,"Pagado",IF($F13>0,"Abono parcial","Pendiente"))) | I13: =IF(OR($B13="",$G13<=0),"",TODAY()-$A13) | J13: =IF($B13="","",IF($G13<=0,"✅ Pagado",IF($I13>30,"🔴 Cóbrale ya ("&$I13&" días)",IF($I13>15,"🟠 Lleva "&$I13&" días","🟢 Reciente ("&$I13&" días)"))))
... F301: =IF($B301="","",SUMIF('Abonos Préstamos'!$B:$B,$B301,'Abonos Préstamos'!$C:$C)) | G301: =IF($B301="","",MAX($E301-$F301,0)) | H301: =IF($B301="","",IF($G301<=0,"Pagado",IF($F301>0,"Abono parcial","Pendiente"))) | I301: =IF(OR($B301="",$G301<=0),"",TODAY()-$A301) | J301: =IF($B301="","",IF($G301<=0,"✅ Pagado",IF($I301>30,"🔴 Cóbrale ya ("&$I301&" días)",IF($I301>15,"🟠 Lleva "&$I301&" días","🟢 Reciente ("&$I301&" días)"))))

Sheet Abonos Préstamos
A1: Fecha | B1: Persona | C1: Valor Abonado | D1: Forma de Cobro | E1: Nota | G1: Cada vez que te devuelven plata de un préstamo, anótalo aquí (con su fecha y cómo te pagaron).

Sheet Inventario
A1: Código | B1: Producto | C1: Categoría | D1: Costo Promedio | E1: Stock Casa | F1: Stock Mercado Libre | G1: Stock Total | H1: Valor Inventario | I1: Estado
A2: =IF('Catálogo'!$A2="","",'Catálogo'!$A2) | B2: =IF('Catálogo'!$A2="","",'Catálogo'!$B2) | C2: =IF('Catálogo'!$A2="","",'Catálogo'!$C2) | D2: =IF('Catálogo'!$A2="","",'Catálogo'!$F2) | E2: =IF('Catálogo'!$A2="","",'Catálogo'!$G2) | F2: =IF('Catálogo'!$A2="","",'Catálogo'!$H2) | G2: =IF('Catálogo'!$A2="","",'Catálogo'!$I2) | H2: =IF('Catálogo'!$A2="","",'Catálogo'!$J2) | I2: =IF('Catálogo'!$A2="","",'Catálogo'!$K2)
A3: =IF('Catálogo'!$A3="","",'Catálogo'!$A3) | B3: =IF('Catálogo'!$A3="","",'Catálogo'!$B3) | C3: =IF('Catálogo'!$A3="","",'Catálogo'!$C3) | D3: =IF('Catálogo'!$A3="","",'Catálogo'!$F3) | E3: =IF('Catálogo'!$A3="","",'Catálogo'!$G3) | F3: =IF('Catálogo'!$A3="","",'Catálogo'!$H3) | G3: =IF('Catálogo'!$A3="","",'Catálogo'!$I3) | H3: =IF('Catálogo'!$A3="","",'Catálogo'!$J3) | I3: =IF('Catálogo'!$A3="","",'Catálogo'!$K3)
A4: =IF('Catálogo'!$A4="","",'Catálogo'!$A4) | B4: =IF('Catálogo'!$A4="","",'Catálogo'!$B4) | C4: =IF('Catálogo'!$A4="","",'Catálogo'!$C4) | D4: =IF('Catálogo'!$A4="","",'Catálogo'!$F4) | E4: =IF('Catálogo'!$A4="","",'Catálogo'!$G4) | F4: =IF('Catálogo'!$A4="","",'Catálogo'!$H4) | G4: =IF('Catálogo'!$A4="","",'Catálogo'!$I4) | H4: =IF('Catálogo'!$A4="","",'Catálogo'!$J4) | I4: =IF('Catálogo'!$A4="","",'Catálogo'!$K4)
A5: =IF('Catálogo'!$A5="","",'Catálogo'!$A5) | B5: =IF('Catálogo'!$A5="","",'Catálogo'!$B5) | C5: =IF('Catálogo'!$A5="","",'Catálogo'!$C5) | D5: =IF('Catálogo'!$A5="","",'Catálogo'!$F5) | E5: =IF('Catálogo'!$A5="","",'Catálogo'!$G5) | F5: =IF('Catálogo'!$A5="","",'Catálogo'!$H5) | G5: =IF('Catálogo'!$A5="","",'Catálogo'!$I5) | H5: =IF('Catálogo'!$A5="","",'Catálogo'!$J5) | I5: =IF('Catálogo'!$A5="","",'Catálogo'!$K5)
A6: =IF('Catálogo'!$A6="","",'Catálogo'!$A6) | B6: =IF('Catálogo'!$A6="","",'Catálogo'!$B6) | C6: =IF('Catálogo'!$A6="","",'Catálogo'!$C6) | D6: =IF('Catálogo'!$A6="","",'Catálogo'!$F6) | E6: =IF('Catálogo'!$A6="","",'Catálogo'!$G6) | F6: =IF('Catálogo'!$A6="","",'Catálogo'!$H6) | G6: =IF('Catálogo'!$A6="","",'Catálogo'!$I6) | H6: =IF('Catálogo'!$A6="","",'Catálogo'!$J6) | I6: =IF('Catálogo'!$A6="","",'Catálogo'!$K6)
A7: =IF('Catálogo'!$A7="","",'Catálogo'!$A7) | B7: =IF('Catálogo'!$A7="","",'Catálogo'!$B7) | C7: =IF('Catálogo'!$A7="","",'Catálogo'!$C7) | D7: =IF('Catálogo'!$A7="","",'Catálogo'!$F7) | E7: =IF('Catálogo'!$A7="","",'Catálogo'!$G7) | F7: =IF('Catálogo'!$A7="","",'Catálogo'!$H7) | G7: =IF('Catálogo'!$A7="","",'Catálogo'!$I7) | H7: =IF('Catálogo'!$A7="","",'Catálogo'!$J7) | I7: =IF('Catálogo'!$A7="","",'Catálogo'!$K7)
A8: =IF('Catálogo'!$A8="","",'Catálogo'!$A8) | B8: =IF('Catálogo'!$A8="","",'Catálogo'!$B8) | C8: =IF('Catálogo'!$A8="","",'Catálogo'!$C8) | D8: =IF('Catálogo'!$A8="","",'Catálogo'!$F8) | E8: =IF('Catálogo'!$A8="","",'Catálogo'!$G8) | F8: =IF('Catálogo'!$A8="","",'Catálogo'!$H8) | G8: =IF('Catálogo'!$A8="","",'Catálogo'!$I8) | H8: =IF('Catálogo'!$A8="","",'Catálogo'!$J8) | I8: =IF('Catálogo'!$A8="","",'Catálogo'!$K8)
A9: =IF('Catálogo'!$A9="","",'Catálogo'!$A9) | B9: =IF('Catálogo'!$A9="","",'Catálogo'!$B9) | C9: =IF('Catálogo'!$A9="","",'Catálogo'!$C9) | D9: =IF('Catálogo'!$A9="","",'Catálogo'!$F9) | E9: =IF('Catálogo'!$A9="","",'Catálogo'!$G9) | F9: =IF('Catálogo'!$A9="","",'Catálogo'!$H9) | G9: =IF('Catálogo'!$A9="","",'Catálogo'!$I9) | H9: =IF('Catálogo'!$A9="","",'Catálogo'!$J9) | I9: =IF('Catálogo'!$A9="","",'Catálogo'!$K9)
A10: =IF('Catálogo'!$A10="","",'Catálogo'!$A10) | B10: =IF('Catálogo'!$A10="","",'Catálogo'!$B10) | C10: =IF('Catálogo'!$A10="","",'Catálogo'!$C10) | D10: =IF('Catálogo'!$A10="","",'Catálogo'!$F10) | E10: =IF('Catálogo'!$A10="","",'Catálogo'!$G10) | F10: =IF('Catálogo'!$A10="","",'Catálogo'!$H10) | G10: =IF('Catálogo'!$A10="","",'Catálogo'!$I10) | H10: =IF('Catálogo'!$A10="","",'Catálogo'!$J10) | I10: =IF('Catálogo'!$A10="","",'Catálogo'!$K10)
A11: =IF('Catálogo'!$A11="","",'Catálogo'!$A11) | B11: =IF('Catálogo'!$A11="","",'Catálogo'!$B11) | C11: =IF('Catálogo'!$A11="","",'Catálogo'!$C11) | D11: =IF('Catálogo'!$A11="","",'Catálogo'!$F11) | E11: =IF('Catálogo'!$A11="","",'Catálogo'!$G11) | F11: =IF('Catálogo'!$A11="","",'Catálogo'!$H11) | G11: =IF('Catálogo'!$A11="","",'Catálogo'!$I11) | H11: =IF('Catálogo'!$A11="","",'Catálogo'!$J11) | I11: =IF('Catálogo'!$A11="","",'Catálogo'!$K11)
A12: =IF('Catálogo'!$A12="","",'Catálogo'!$A12) | B12: =IF('Catálogo'!$A12="","",'Catálogo'!$B12) | C12: =IF('Catálogo'!$A12="","",'Catálogo'!$C12) | D12: =IF('Catálogo'!$A12="","",'Catálogo'!$F12) | E12: =IF('Catálogo'!$A12="","",'Catálogo'!$G12) | F12: =IF('Catálogo'!$A12="","",'Catálogo'!$H12) | G12: =IF('Catálogo'!$A12="","",'Catálogo'!$I12) | H12: =IF('Catálogo'!$A12="","",'Catálogo'!$J12) | I12: =IF('Catálogo'!$A12="","",'Catálogo'!$K12)
A13: =IF('Catálogo'!$A13="","",'Catálogo'!$A13) | B13: =IF('Catálogo'!$A13="","",'Catálogo'!$B13) | C13: =IF('Catálogo'!$A13="","",'Catálogo'!$C13) | D13: =IF('Catálogo'!$A13="","",'Catálogo'!$F13) | E13: =IF('Catálogo'!$A13="","",'Catálogo'!$G13) | F13: =IF('Catálogo'!$A13="","",'Catálogo'!$H13) | G13: =IF('Catálogo'!$A13="","",'Catálogo'!$I13) | H13: =IF('Catálogo'!$A13="","",'Catálogo'!$J13) | I13: =IF('Catálogo'!$A13="","",'Catálogo'!$K13)
... A201: =IF('Catálogo'!$A201="","",'Catálogo'!$A201) | B201: =IF('Catálogo'!$A201="","",'Catálogo'!$B201) | C201: =IF('Catálogo'!$A201="","",'Catálogo'!$C201) | D201: =IF('Catálogo'!$A201="","",'Catálogo'!$F201) | E201: =IF('Catálogo'!$A201="","",'Catálogo'!$G201) | F201: =IF('Catálogo'!$A201="","",'Catálogo'!$H201) | G201: =IF('Catálogo'!$A201="","",'Catálogo'!$I201) | H201: =IF('Catálogo'!$A201="","",'Catálogo'!$J201) | I201: =IF('Catálogo'!$A201="","",'Catálogo'!$K201)

Sheet Clientes
A1: ID | B1: Nombre | C1: Documento / NIT | D1: Teléfono | E1: Correo | F1: Dirección | G1: Ciudad | H1: Notas
A2: =IF($B2="","","CLI-"&TEXT(ROW()-1,"000"))
A3: =IF($B3="","","CLI-"&TEXT(ROW()-1,"000"))
A4: =IF($B4="","","CLI-"&TEXT(ROW()-1,"000"))
A5: =IF($B5="","","CLI-"&TEXT(ROW()-1,"000"))
A6: =IF($B6="","","CLI-"&TEXT(ROW()-1,"000"))
A7: =IF($B7="","","CLI-"&TEXT(ROW()-1,"000"))
A8: =IF($B8="","","CLI-"&TEXT(ROW()-1,"000"))
A9: =IF($B9="","","CLI-"&TEXT(ROW()-1,"000"))
A10: =IF($B10="","","CLI-"&TEXT(ROW()-1,"000"))
A11: =IF($B11="","","CLI-"&TEXT(ROW()-1,"000"))
A12: =IF($B12="","","CLI-"&TEXT(ROW()-1,"000"))
A13: =IF($B13="","","CLI-"&TEXT(ROW()-1,"000"))
... A101: =IF($B101="","","CLI-"&TEXT(ROW()-1,"000"))

Sheet Factura
A1: LOGO | B1: ='Config'!$B$2 | D1: FACTURA DE VENTA
B2: ="NIT: "&'Config'!$B$3 | D2: Venta N°:
B3: ='Config'!$B$4 | D3: Fecha: | E3: =IFERROR(INDEX('Ventas'!$A$2:$A$2000,MATCH($E$2,'Ventas'!$B$2:$B$2000,0)),"")
B4: ="Tel: "&'Config'!$B$5&" | "&'Config'!$B$6 | D4: Pago: | E4: =IFERROR(INDEX('Ventas'!$O$2:$O$2000,MATCH($E$2,'Ventas'!$B$2:$B$2000,0)),"")
B5: ='Config'!$B$7 | D5: Origen inv.: | E5: =IFERROR(INDEX('Ventas'!$G$2:$G$2000,MATCH($E$2,'Ventas'!$B$2:$B$2000,0)),"")
A7: DATOS DEL CLIENTE
A8: Cliente: | B8: =IFERROR(INDEX('Ventas'!$C$2:$C$2000,MATCH($E$2,'Ventas'!$B$2:$B$2000,0)),"") | D8: Documento: | E8: =IFERROR(VLOOKUP($B$8,'Clientes'!$B:$F,2,FALSE),"")
A9: Teléfono: | B9: =IFERROR(VLOOKUP($B$8,'Clientes'!$B:$F,3,FALSE),"") | D9: Correo: | E9: =IFERROR(VLOOKUP($B$8,'Clientes'!$B:$F,4,FALSE),"")
A10: Dirección: | B10: =IFERROR(VLOOKUP($B$8,'Clientes'!$B:$F,5,FALSE),"")
A12: Código | B12: Descripción | D12: Cant. | E12: Vr. Unitario | F12: Total
A13: =IF($J13="","",$J13) | B13: =IF($A13="","",IFERROR(VLOOKUP($A13,'Catálogo'!$A:$B,2,FALSE),"")) | D13: =IF($J13="","",$L13) | E13: =IF(OR($J13="",$L13=0),"",$N13/$L13) | F13: =IF($A13="","",$D13*$E13) | G13: =IF($A13="","",IFERROR(VLOOKUP($A13,'Catálogo'!$A:$L,12,FALSE),0)) | H13: =IF($F13="","",ROUND($F13*$G13/100,0)) | J13: =IFERROR(FILTER('Ventas'!$D$2:$H$2000,'Ventas'!$B$2:$B$2000=$E$2),"")
A14: =IF($J14="","",$J14) | B14: =IF($A14="","",IFERROR(VLOOKUP($A14,'Catálogo'!$A:$B,2,FALSE),"")) | D14: =IF($J14="","",$L14) | E14: =IF(OR($J14="",$L14=0),"",$N14/$L14) | F14: =IF($A14="","",$D14*$E14) | G14: =IF($A14="","",IFERROR(VLOOKUP($A14,'Catálogo'!$A:$L,12,FALSE),0)) | H14: =IF($F14="","",ROUND($F14*$G14/100,0))
A15: =IF($J15="","",$J15) | B15: =IF($A15="","",IFERROR(VLOOKUP($A15,'Catálogo'!$A:$B,2,FALSE),"")) | D15: =IF($J15="","",$L15) | E15: =IF(OR($J15="",$L15=0),"",$N15/$L15) | F15: =IF($A15="","",$D15*$E15) | G15: =IF($A15="","",IFERROR(VLOOKUP($A15,'Catálogo'!$A:$L,12,FALSE),0)) | H15: =IF($F15="","",ROUND($F15*$G15/100,0))
A16: =IF($J16="","",$J16) | B16: =IF($A16="","",IFERROR(VLOOKUP($A16,'Catálogo'!$A:$B,2,FALSE),"")) | D16: =IF($J16="","",$L16) | E16: =IF(OR($J16="",$L16=0),"",$N16/$L16) | F16: =IF($A16="","",$D16*$E16) | G16: =IF($A16="","",IFERROR(VLOOKUP($A16,'Catálogo'!$A:$L,12,FALSE),0)) | H16: =IF($F16="","",ROUND($F16*$G16/100,0))
A17: =IF($J17="","",$J17) | B17: =IF($A17="","",IFERROR(VLOOKUP($A17,'Catálogo'!$A:$B,2,FALSE),"")) | D17: =IF($J17="","",$L17) | E17: =IF(OR($J17="",$L17=0),"",$N17/$L17) | F17: =IF($A17="","",$D17*$E17) | G17: =IF($A17="","",IFERROR(VLOOKUP($A17,'Catálogo'!$A:$L,12,FALSE),0)) | H17: =IF($F17="","",ROUND($F17*$G17/100,0))
A18: =IF($J18="","",$J18) | B18: =IF($A18="","",IFERROR(VLOOKUP($A18,'Catálogo'!$A:$B,2,FALSE),"")) | D18: =IF($J18="","",$L18) | E18: =IF(OR($J18="",$L18=0),"",$N18/$L18) | F18: =IF($A18="","",$D18*$E18) | G18: =IF($A18="","",IFERROR(VLOOKUP($A18,'Catálogo'!$A:$L,12,FALSE),0)) | H18: =IF($F18="","",ROUND($F18*$G18/100,0))
A19: =IF($J19="","",$J19) | B19: =IF($A19="","",IFERROR(VLOOKUP($A19,'Catálogo'!$A:$B,2,FALSE),"")) | D19: =IF($J19="","",$L19) | E19: =IF(OR($J19="",$L19=0),"",$N19/$L19) | F19: =IF($A19="","",$D19*$E19) | G19: =IF($A19="","",IFERROR(VLOOKUP($A19,'Catálogo'!$A:$L,12,FALSE),0)) | H19: =IF($F19="","",ROUND($F19*$G19/100,0))
A20: =IF($J20="","",$J20) | B20: =IF($A20="","",IFERROR(VLOOKUP($A20,'Catálogo'!$A:$B,2,FALSE),"")) | D20: =IF($J20="","",$L20) | E20: =IF(OR($J20="",$L20=0),"",$N20/$L20) | F20: =IF($A20="","",$D20*$E20) | G20: =IF($A20="","",IFERROR(VLOOKUP($A20,'Catálogo'!$A:$L,12,FALSE),0)) | H20: =IF($F20="","",ROUND($F20*$G20/100,0))
A21: =IF($J21="","",$J21) | B21: =IF($A21="","",IFERROR(VLOOKUP($A21,'Catálogo'!$A:$B,2,FALSE),"")) | D21: =IF($J21="","",$L21) | E21: =IF(OR($J21="",$L21=0),"",$N21/$L21) | F21: =IF($A21="","",$D21*$E21) | G21: =IF($A21="","",IFERROR(VLOOKUP($A21,'Catálogo'!$A:$L,12,FALSE),0)) | H21: =IF($F21="","",ROUND($F21*$G21/100,0))
A22: =IF($J22="","",$J22) | B22: =IF($A22="","",IFERROR(VLOOKUP($A22,'Catálogo'!$A:$B,2,FALSE),"")) | D22: =IF($J22="","",$L22) | E22: =IF(OR($J22="",$L22=0),"",$N22/$L22) | F22: =IF($A22="","",$D22*$E22) | G22: =IF($A22="","",IFERROR(VLOOKUP($A22,'Catálogo'!$A:$L,12,FALSE),0)) | H22: =IF($F22="","",ROUND($F22*$G22/100,0))
A23: =IF($J23="","",$J23) | B23: =IF($A23="","",IFERROR(VLOOKUP($A23,'Catálogo'!$A:$B,2,FALSE),"")) | D23: =IF($J23="","",$L23) | E23: =IF(OR($J23="",$L23=0),"",$N23/$L23) | F23: =IF($A23="","",$D23*$E23) | G23: =IF($A23="","",IFERROR(VLOOKUP($A23,'Catálogo'!$A:$L,12,FALSE),0)) | H23: =IF($F23="","",ROUND($F23*$G23/100,0))
A24: =IF($J24="","",$J24) | B24: =IF($A24="","",IFERROR(VLOOKUP($A24,'Catálogo'!$A:$B,2,FALSE),"")) | D24: =IF($J24="","",$L24) | E24: =IF(OR($J24="",$L24=0),"",$N24/$L24) | F24: =IF($A24="","",$D24*$E24) | G24: =IF($A24="","",IFERROR(VLOOKUP($A24,'Catálogo'!$A:$L,12,FALSE),0)) | H24: =IF($F24="","",ROUND($F24*$G24/100,0))
A25: Observaciones:
D26: Subtotal: | F26: =SUM($F$13:$F$24)
D27: IVA: | F27: =SUM($H$13:$H$24)
D28: TOTAL A PAGAR: | F28: =$F$26+$F$27
A31: ='Config'!$B$10
A32: Documento generado electrónicamente · Sistema de Gestión

Sheet Catálogo Venta
A1: ='Config'!$B$2
A2: ="Catálogo de productos · "&$B$3&" · Precio "&$D$3
A3: Categoría: | B3: TODAS | C3: Tipo de precio: | D3: Detal
A5: Imagen | B5: Producto | C5: Medidas / Código | D5: Precio | E5: Disp. Casa (und)
A6: =IF($H6="","",IFERROR(IMAGE($T6,1),"")) | B6: =IF($H6="","",$I6) | C6: =IF($H6="","",IF($Y6="","Cód: "&$H6,"Medidas: "&$Y6&" · Cód: "&$H6)) | D6: =IF($H6="","",IF($D$3="Mayor",$V6,$U6)) | E6: =IF($H6="","",$N6) | H6: =IFERROR(SORT(FILTER('Catálogo'!$A$2:$R$2000,('Catálogo'!$A$2:$A$2000<>"")*('Catálogo'!$D$2:$D$2000<>"Inactivo")*(($B$3="TODAS")+('Catálogo'!$C$2:$C$2000=$B$3))),3,TRUE,18,TRUE,2,TRUE),"")
A7: =IF($H7="","",IFERROR(IMAGE($T7,1),"")) | B7: =IF($H7="","",$I7) | C7: =IF($H7="","",IF($Y7="","Cód: "&$H7,"Medidas: "&$Y7&" · Cód: "&$H7)) | D7: =IF($H7="","",IF($D$3="Mayor",$V7,$U7)) | E7: =IF($H7="","",$N7)
A8: =IF($H8="","",IFERROR(IMAGE($T8,1),"")) | B8: =IF($H8="","",$I8) | C8: =IF($H8="","",IF($Y8="","Cód: "&$H8,"Medidas: "&$Y8&" · Cód: "&$H8)) | D8: =IF($H8="","",IF($D$3="Mayor",$V8,$U8)) | E8: =IF($H8="","",$N8)
A9: =IF($H9="","",IFERROR(IMAGE($T9,1),"")) | B9: =IF($H9="","",$I9) | C9: =IF($H9="","",IF($Y9="","Cód: "&$H9,"Medidas: "&$Y9&" · Cód: "&$H9)) | D9: =IF($H9="","",IF($D$3="Mayor",$V9,$U9)) | E9: =IF($H9="","",$N9)
A10: =IF($H10="","",IFERROR(IMAGE($T10,1),"")) | B10: =IF($H10="","",$I10) | C10: =IF($H10="","",IF($Y10="","Cód: "&$H10,"Medidas: "&$Y10&" · Cód: "&$H10)) | D10: =IF($H10="","",IF($D$3="Mayor",$V10,$U10)) | E10: =IF($H10="","",$N10)
A11: =IF($H11="","",IFERROR(IMAGE($T11,1),"")) | B11: =IF($H11="","",$I11) | C11: =IF($H11="","",IF($Y11="","Cód: "&$H11,"Medidas: "&$Y11&" · Cód: "&$H11)) | D11: =IF($H11="","",IF($D$3="Mayor",$V11,$U11)) | E11: =IF($H11="","",$N11)
A12: =IF($H12="","",IFERROR(IMAGE($T12,1),"")) | B12: =IF($H12="","",$I12) | C12: =IF($H12="","",IF($Y12="","Cód: "&$H12,"Medidas: "&$Y12&" · Cód: "&$H12)) | D12: =IF($H12="","",IF($D$3="Mayor",$V12,$U12)) | E12: =IF($H12="","",$N12)
A13: =IF($H13="","",IFERROR(IMAGE($T13,1),"")) | B13: =IF($H13="","",$I13) | C13: =IF($H13="","",IF($Y13="","Cód: "&$H13,"Medidas: "&$Y13&" · Cód: "&$H13)) | D13: =IF($H13="","",IF($D$3="Mayor",$V13,$U13)) | E13: =IF($H13="","",$N13)
A14: =IF($H14="","",IFERROR(IMAGE($T14,1),"")) | B14: =IF($H14="","",$I14) | C14: =IF($H14="","",IF($Y14="","Cód: "&$H14,"Medidas: "&$Y14&" · Cód: "&$H14)) | D14: =IF($H14="","",IF($D$3="Mayor",$V14,$U14)) | E14: =IF($H14="","",$N14)
A15: =IF($H15="","",IFERROR(IMAGE($T15,1),"")) | B15: =IF($H15="","",$I15) | C15: =IF($H15="","",IF($Y15="","Cód: "&$H15,"Medidas: "&$Y15&" · Cód: "&$H15)) | D15: =IF($H15="","",IF($D$3="Mayor",$V15,$U15)) | E15: =IF($H15="","",$N15)
A16: =IF($H16="","",IFERROR(IMAGE($T16,1),"")) | B16: =IF($H16="","",$I16) | C16: =IF($H16="","",IF($Y16="","Cód: "&$H16,"Medidas: "&$Y16&" · Cód: "&$H16)) | D16: =IF($H16="","",IF($D$3="Mayor",$V16,$U16)) | E16: =IF($H16="","",$N16)
A17: =IF($H17="","",IFERROR(IMAGE($T17,1),"")) | B17: =IF($H17="","",$I17) | C17: =IF($H17="","",IF($Y17="","Cód: "&$H17,"Medidas: "&$Y17&" · Cód: "&$H17)) | D17: =IF($H17="","",IF($D$3="Mayor",$V17,$U17)) | E17: =IF($H17="","",$N17)
A18: =IF($H18="","",IFERROR(IMAGE($T18,1),"")) | B18: =IF($H18="","",$I18) | C18: =IF($H18="","",IF($Y18="","Cód: "&$H18,"Medidas: "&$Y18&" · Cód: "&$H18)) | D18: =IF($H18="","",IF($D$3="Mayor",$V18,$U18)) | E18: =IF($H18="","",$N18)
... A255: =IF($H255="","",IFERROR(IMAGE($T255,1),"")) | B255: =IF($H255="","",$I255) | C255: =IF($H255="","",IF($Y255="","Cód: "&$H255,"Medidas: "&$Y255&" · Cód: "&$H255)) | D255: =IF($H255="","",IF($D$3="Mayor",$V255,$U255)) | E255: =IF($H255="","",$N255)

Sheet Config
A1: Parámetro | B1: Valor | D1: Categorías | E1: IVA % | F1: Ubicaciones | H1: Estados | J1: Motivos de ajuste | L1: Selección catálogo | N1: Tarjetas de crédito | P1: Billeteras (formas de cobro) | R1: Medio de compra (billetera o tarjeta)
A2: Nombre de la empresa | B2: Mi Negocio S.A.S. | D2: General | F2: Casa | H2: Activo | J2: Producto dañado | L2: TODAS | N2: TC Bancolombia 1 (1517) | P2: Efectivo | R2: Inventario inicial (ya pagado)
A3: NIT / Identificación | B3: 000.000.000-0 | D3: Electrónica | F3: Mercado Libre | H3: Inactivo | J3: Pérdida | L3: =IF($D2="","",$D2) | N3: TC Bancolombia 2 (0554) | P3: Nequi | R3: Efectivo
A4: Dirección | B4: Calle 00 # 00-00, Ciudad | D4: Hogar | J4: Corrección de conteo | L4: =IF($D3="","",$D3) | N4: TC Bancolombia 3 (4582) | P4: Bancolombia | R4: Nequi
A5: Teléfono | B5: +57 300 000 0000 | D5: Ropa y calzado | J5: Ajuste administrativo | L5: =IF($D4="","",$D4) | N5: TC Bancolombia 4 (8366) | P5: Bancolombia MM | R5: Bancolombia
A6: Correo electrónico | B6: correo@minegocio.com | D6: Accesorios | J6: Devolución | L6: =IF($D5="","",$D5) | N6: TC Bancolombia 5 (0623) | P6: Daviplata | R6: Bancolombia MM
A7: Sitio web | B7: www.minegocio.com | D7: Papelería | L7: =IF($D6="","",$D6) | N7: TC Bancolombia MM 6 (6423) | P7: Davivienda | R7: Daviplata
A8: Prefijo de factura | B8: FAC- | D8: Arte | L8: =IF($D7="","",$D7) | N8: TC Bancolombia MM 7 (2459) | P8: Mercado Libre | R8: Davivienda
A9: Próximo número de factura | B9: 1 | D9: Otros | L9: =IF($D8="","",$D8) | N9: TC NU 8 (3750) | P9: Skydrops | R9: Mercado Libre
A10: Mensaje pie de factura | B10: ¡Gracias por su compra! | L10: =IF($D9="","",$D9) | R10: Skydrops
A11: Costo fijo por venta: envío (Mary) | B11: 1000 | L11: =IF($D10="","",$D10) | R11: TC Bancolombia 1 (1517)
A12: Costo fijo por venta: bolsa y etiqueta | B12: 1000 | L12: =IF($D11="","",$D11) | R12: TC Bancolombia 2 (0554)
A13: Día de cierre de tarjeta | B13: 30 | L13: =IF($D12="","",$D12) | R13: TC Bancolombia 3 (4582)
A14: Día de pago de tarjeta | B14: 16 | L14: =IF($D13="","",$D13) | R14: TC Bancolombia 4 (8366)
A15: Avisar si faltan (días) o menos | B15: 5 | L15: =IF($D14="","",$D14) | R15: TC Bancolombia 5 (0623)
L16: =IF($D15="","",$D15) | R16: TC Bancolombia MM 6 (6423)
L17: =IF($D16="","",$D16) | R17: TC Bancolombia MM 7 (2459)
L18: =IF($D17="","",$D17) | R18: TC NU 8 (3750)
L19: =IF($D18="","",$D18)
L20: =IF($D19="","",$D19)
L21: =IF($D20="","",$D20)
L22: =IF($D21="","",$D21)
L23: =IF($D22="","",$D22)
L24: =IF($D23="","",$D23)
L25: =IF($D24="","",$D24)
L26: =IF($D25="","",$D25)
L27: =IF($D26="","",$D26)
L28: =IF($D27="","",$D27)
L29: =IF($D28="","",$D28)
L30: =IF($D29="","",$D29)
